[
  {
    "appearanceLog": [
      {
        "time": "2025-09-22T21:21:19.603Z",
        "type": "FOUND"
      }
    ],
    "artists": [
      "Alexjazz"
    ],
    "artistsPopularity": 3,
    "imageUrl": "https://i.scdn.co/image/ab67616d0000b27386a7d13aa6a90871944da319",
    "releaseDate": "2021-07-09",
    "tags": [
      "post-punk"
    ],
    "title": "Ф'южн",
    "totalTracks": 10,
    "type": "album",
    "url": "https://open.spotify.com/album/0ZJNpldfT4BlWHjIrVKOEh"
  },
  {
    "appearanceLog": [
      {
        "time": "2025-09-22T21:21:19.603Z",
        "type": "FOUND"
      }
    ],
    "artists": [
      "Alexjazz",
      "The Cancel"
    ],
    "artistsPopularity": 5,
    "imageUrl": "https://i.scdn.co/image/ab67616d0000b273f41f67dd263cb0e68c865fc0",
    "releaseDate": "2014-11-07",
    "tags": [
      "post-punk",
      "instrumental hip-hop",
      "abstract hip-hop"
    ],
    "title": "Panorama",
    "totalTracks": 11,
    "type": "album",
    "url": "https://open.spotify.com/album/5QeAvSuxdVHKIQJPLq4tWM"
  },
  {
    "appearanceLog": [
      {
        "time": "2025-09-22T21:21:19.603Z",
        "type": "FOUND"
      }
    ],
    "artists": [
      "Alexjazz"
    ],
    "artistsPopularity": 3,
    "imageUrl": "https://i.scdn.co/image/ab67616d0000b2738a85a3b37087ea5e5424998e",
    "releaseDate": "2013-09-14",
    "tags": [
      "post-punk"
    ],
    "title": "Photoalbum",
    "totalTracks": 13,
    "type": "album",
    "url": "https://open.spotify.com/album/6VBlQM25Mb1t5BSo3aMhCh"
  },
  {
    "appearanceLog": [
      {
        "time": "2025-09-22T21:21:19.603Z",
        "type": "FOUND"
      }
    ],
    "artists": [
      "Alexjazz"
    ],
    "artistsPopularity": 3,
    "imageUrl": "https://i.scdn.co/image/ab67616d0000b2735ffb92b2e0ebdfcac06b28ab",
    "releaseDate": "2025-08-08",
    "tags": [
      "post-punk"
    ],
    "title": "Чорне",
    "totalTracks": 1,
    "type": "single",
    "url": "https://open.spotify.com/album/6IAFWMz2CN55qpSUvF1oDs"
  },
  {
    "appearanceLog": [
      {
        "time": "2025-09-22T21:21:19.603Z",
        "type": "FOUND"
      }
    ],
    "artists": [
      "Alexjazz"
    ],
    "artistsPopularity": 3,
    "imageUrl": "https://i.scdn.co/image/ab67616d0000b273c680d914737213af8f267876",
    "releaseDate": "2025-04-04",
    "tags": [
      "post-punk"
    ],
    "title": "Твоє ім'я",
    "totalTracks": 1,
    "type": "single",
    "url": "https://open.spotify.com/album/56K5Fpd7JTNgg3jL6XjjDk"
  },
  {
    "appearanceLog": [
      {
        "time": "2025-09-22T21:21:19.603Z",
        "type": "FOUND"
      }
    ],
    "artists": [
      "Alexjazz"
    ],
    "artistsPopularity": 3,
    "imageUrl": "https://i.scdn.co/image/ab67616d0000b2738a6d6780670d51041aa2f83d",
    "releaseDate": "2025-02-21",
    "tags": [
      "post-punk"
    ],
    "title": "Кохай мене",
    "totalTracks": 1,
    "type": "single",
    "url": "https://open.spotify.com/album/0PEPLm6weaambaC3JOiNBE"
  },
  {
    "appearanceLog": [
      {
        "time": "2025-09-22T21:21:19.603Z",
        "type": "FOUND"
      }
    ],
    "artists": [
      "Alexjazz"
    ],
    "artistsPopularity": 3,
    "imageUrl": "https://i.scdn.co/image/ab67616d0000b27332da4f4065ef8c43de2a3858",
    "releaseDate": "2024-12-05",
    "tags": [
      "post-punk"
    ],
    "title": "Вітер",
    "totalTracks": 1,
    "type": "single",
    "url": "https://open.spotify.com/album/35Zx96RzxYiYdva2uMj07E"
  },
  {
    "appearanceLog": [
      {
        "time": "2025-09-22T21:21:19.603Z",
        "type": "FOUND"
      }
    ],
    "artists": [
      "Alexjazz",
      "Колос"
    ],
    "artistsPopularity": 3,
    "imageUrl": "https://i.scdn.co/image/ab67616d0000b27379ad447ba33aaa6c2e68e646",
    "releaseDate": "2024-10-18",
    "tags": [
      "rock",
      "post-punk",
      "acoustic",
      "noise"
    ],
    "title": "Не збагнув",
    "totalTracks": 1,
    "type": "single",
    "url": "https://open.spotify.com/album/6W4KWqmBxzGSSrPJe5MtQw"
  },
  {
    "appearanceLog": [
      {
        "time": "2025-09-22T21:21:19.603Z",
        "type": "FOUND"
      }
    ],
    "artists": [
      "Alexjazz"
    ],
    "artistsPopularity": 3,
    "imageUrl": "https://i.scdn.co/image/ab67616d0000b273b8f390d724efc979e659c564",
    "releaseDate": "2024-06-28",
    "tags": [
      "post-punk"
    ],
    "title": "Моя любов",
    "totalTracks": 1,
    "type": "single",
    "url": "https://open.spotify.com/album/6iQodPyd7mZgWBuzFLV5YH"
  },
  {
    "appearanceLog": [
      {
        "time": "2025-09-22T21:21:19.603Z",
        "type": "FOUND"
      }
    ],
    "artists": [
      "Alexjazz"
    ],
    "artistsPopularity": 3,
    "imageUrl": "https://i.scdn.co/image/ab67616d0000b2739f51174f3b08fbf1b2133299",
    "releaseDate": "2024-05-17",
    "tags": [
      "post-punk"
    ],
    "title": "Були квітами",
    "totalTracks": 1,
    "type": "single",
    "url": "https://open.spotify.com/album/5cgKQP79KQsUF9CHfIrQZH"
  },
  {
    "appearanceLog": [
      {
        "time": "2025-09-22T21:21:19.603Z",
        "type": "FOUND"
      }
    ],
    "artists": [
      "Alexjazz"
    ],
    "artistsPopularity": 3,
    "imageUrl": "https://i.scdn.co/image/ab67616d0000b273329b28cf542e6fda80007915",
    "releaseDate": "2024-03-22",
    "tags": [
      "post-punk"
    ],
    "title": "Меланхолія",
    "totalTracks": 1,
    "type": "single",
    "url": "https://open.spotify.com/album/18vwi9S4ZiL7LnBqapohP8"
  },
  {
    "appearanceLog": [
      {
        "time": "2025-09-22T21:21:19.603Z",
        "type": "FOUND"
      }
    ],
    "artists": [
      "Alexjazz"
    ],
    "artistsPopularity": 3,
    "imageUrl": "https://i.scdn.co/image/ab67616d0000b2738b9dee81f2e437760521ae37",
    "releaseDate": "2024-01-26",
    "tags": [
      "post-punk"
    ],
    "title": "Так рано",
    "totalTracks": 1,
    "type": "single",
    "url": "https://open.spotify.com/album/5ENh6Z9GQFl4oWx5ibgy2j"
  },
  {
    "appearanceLog": [
      {
        "time": "2025-09-22T21:21:19.603Z",
        "type": "FOUND"
      }
    ],
    "artists": [
      "paashee",
      "Alexjazz"
    ],
    "artistsPopularity": 3,
    "imageUrl": "https://i.scdn.co/image/ab67616d0000b2734a734ddf5f27ffc19583b321",
    "releaseDate": "2023-12-01",
    "tags": [
      "rap",
      "post-punk"
    ],
    "title": "Вітряно",
    "totalTracks": 1,
    "type": "single",
    "url": "https://open.spotify.com/album/51ANSLiWLRXkBl6N0mzA1R"
  },
  {
    "appearanceLog": [
      {
        "time": "2025-09-22T21:21:19.603Z",
        "type": "FOUND"
      }
    ],
    "artists": [
      "Alexjazz"
    ],
    "artistsPopularity": 3,
    "imageUrl": "https://i.scdn.co/image/ab67616d0000b27325f6562d8f79ea9c5ba55486",
    "releaseDate": "2023-09-07",
    "tags": [
      "post-punk"
    ],
    "title": "Хейтспіч",
    "totalTracks": 1,
    "type": "single",
    "url": "https://open.spotify.com/album/0iX1EnjV6YGOK6E8YWFbMO"
  },
  {
    "appearanceLog": [
      {
        "time": "2025-09-22T21:21:19.603Z",
        "type": "FOUND"
      }
    ],
    "artists": [
      "Alexjazz"
    ],
    "artistsPopularity": 3,
    "imageUrl": "https://i.scdn.co/image/ab67616d0000b273a86921605a2657625c0aa73a",
    "releaseDate": "2023-05-26",
    "tags": [
      "post-punk"
    ],
    "title": "Сірники",
    "totalTracks": 1,
    "type": "single",
    "url": "https://open.spotify.com/album/5wEOfX1RXKz4NQi08rrIne"
  },
  {
    "appearanceLog": [
      {
        "time": "2025-09-22T21:21:19.603Z",
        "type": "FOUND"
      }
    ],
    "artists": [
      "Alexjazz"
    ],
    "artistsPopularity": 3,
    "imageUrl": "https://i.scdn.co/image/ab67616d0000b2731afe749e11be9e62ec8dc9da",
    "releaseDate": "2023-05-05",
    "tags": [
      "post-punk"
    ],
    "title": "Інший",
    "totalTracks": 1,
    "type": "single",
    "url": "https://open.spotify.com/album/4A4Cn7tubueJ0DdY5tyasW"
  },
  {
    "appearanceLog": [
      {
        "time": "2025-09-22T21:21:19.603Z",
        "type": "FOUND"
      }
    ],
    "artists": [
      "Alexjazz"
    ],
    "artistsPopularity": 3,
    "imageUrl": "https://i.scdn.co/image/ab67616d0000b273b7c7b8f43ecccc78ec04a15b",
    "releaseDate": "2023-03-24",
    "tags": [
      "post-punk"
    ],
    "title": "Зачекався",
    "totalTracks": 1,
    "type": "single",
    "url": "https://open.spotify.com/album/4OmF4MLaOTNiFWgUUkKjak"
  },
  {
    "appearanceLog": [
      {
        "time": "2025-09-22T21:21:19.603Z",
        "type": "FOUND"
      }
    ],
    "artists": [
      "Alexjazz"
    ],
    "artistsPopularity": 3,
    "imageUrl": "https://i.scdn.co/image/ab67616d0000b27363253ee66219a0a5c4f2fe58",
    "releaseDate": "2022-11-11",
    "tags": [
      "post-punk"
    ],
    "title": "Смутний",
    "totalTracks": 1,
    "type": "single",
    "url": "https://open.spotify.com/album/04GSw9YkN4XlmWSEOFq4XP"
  },
  {
    "appearanceLog": [
      {
        "time": "2025-09-22T21:21:19.603Z",
        "type": "FOUND"
      }
    ],
    "artists": [
      "Alexjazz",
      "Kuba Knap",
      "Roman Sheemy"
    ],
    "artistsPopularity": 4,
    "imageUrl": "https://i.scdn.co/image/ab67616d0000b2734665ddcb40ad691471bb33c9",
    "releaseDate": "2022-10-28",
    "tags": [
      "post-punk",
      "Hip-Hop"
    ],
    "title": "Як справи?",
    "totalTracks": 1,
    "type": "single",
    "url": "https://open.spotify.com/album/4iLF8XIOR9jCRBCGB9gXRp"
  },
  {
    "appearanceLog": [
      {
        "time": "2025-09-22T21:21:19.603Z",
        "type": "FOUND"
      }
    ],
    "artists": [
      "Alexjazz",
      "Oksana Maslo",
      "Roman Sheemy"
    ],
    "artistsPopularity": 3,
    "imageUrl": "https://i.scdn.co/image/ab67616d0000b2731bd80dc9a0eb13e323a6fead",
    "releaseDate": "2022-08-12",
    "tags": [
      "post-punk"
    ],
    "title": "Грай",
    "totalTracks": 1,
    "type": "single",
    "url": "https://open.spotify.com/album/1RJ2wKpVJtmrKy4ofkON7X"
  },
  {
    "appearanceLog": [
      {
        "time": "2025-09-22T21:21:19.603Z",
        "type": "FOUND"
      }
    ],
    "artists": [
      "paashee",
      "Alexjazz",
      "karmv"
    ],
    "artistsPopularity": 3,
    "imageUrl": "https://i.scdn.co/image/ab67616d0000b2735229377399b104c7791b692f",
    "releaseDate": "2022-08-01",
    "tags": [
      "rap",
      "post-punk"
    ],
    "title": "Піксель (Karmv Remix)",
    "totalTracks": 1,
    "type": "single",
    "url": "https://open.spotify.com/album/6Q2y9AnzlaD5hE573WsDXu"
  },
  {
    "appearanceLog": [
      {
        "time": "2025-09-22T21:21:19.603Z",
        "type": "FOUND"
      }
    ],
    "artists": [
      "paashee",
      "Alexjazz"
    ],
    "artistsPopularity": 3,
    "imageUrl": "https://i.scdn.co/image/ab67616d0000b2731084826d046215b7400b50b5",
    "releaseDate": "2022-07-19",
    "tags": [
      "rap",
      "post-punk"
    ],
    "title": "Піксель",
    "totalTracks": 1,
    "type": "single",
    "url": "https://open.spotify.com/album/2rDmrMkMRD9iT1FW3Wwxzp"
  },
  {
    "appearanceLog": [
      {
        "time": "2025-09-22T21:21:19.603Z",
        "type": "FOUND"
      }
    ],
    "artists": [
      "Alexjazz",
      "Oksana Maslo",
      "Dope Price Beats"
    ],
    "artistsPopularity": 3,
    "imageUrl": "https://i.scdn.co/image/ab67616d0000b273dcf5fd2a88ef91d2c66a15cc",
    "releaseDate": "2022-06-02",
    "tags": [
      "post-punk"
    ],
    "title": "Геть! (Remix)",
    "totalTracks": 1,
    "type": "single",
    "url": "https://open.spotify.com/album/26ZNYgHGvTv7nbwG68yrzv"
  },
  {
    "appearanceLog": [
      {
        "time": "2025-09-22T21:21:19.603Z",
        "type": "FOUND"
      }
    ],
    "artists": [
      "Alexjazz",
      "Oksana Maslo",
      "Roman Sheemy"
    ],
    "artistsPopularity": 3,
    "imageUrl": "https://i.scdn.co/image/ab67616d0000b2731dc300c391667ac1c70cc487",
    "releaseDate": "2022-04-15",
    "tags": [
      "post-punk"
    ],
    "title": "Додому",
    "totalTracks": 1,
    "type": "single",
    "url": "https://open.spotify.com/album/1d9tDnvf30IhKcMAfLjWBL"
  },
  {
    "appearanceLog": [
      {
        "time": "2025-09-22T21:21:19.603Z",
        "type": "FOUND"
      }
    ],
    "artists": [
      "Alexjazz",
      "Oksana Maslo",
      "Jointjay"
    ],
    "artistsPopularity": 3,
    "imageUrl": "https://i.scdn.co/image/ab67616d0000b273f894453f6e726c8c13cb53a9",
    "releaseDate": "2022-03-25",
    "tags": [
      "post-punk"
    ],
    "title": "Геть!",
    "totalTracks": 1,
    "type": "single",
    "url": "https://open.spotify.com/album/6ld06yv1tERr7kinHapEP8"
  },
  {
    "appearanceLog": [
      {
        "time": "2025-09-22T21:21:19.603Z",
        "type": "FOUND"
      }
    ],
    "artists": [
      "C23",
      "Alexjazz"
    ],
    "artistsPopularity": 3,
    "imageUrl": "https://i.scdn.co/image/ab67616d0000b2734f0d1880af60b510dea6a331",
    "releaseDate": "2021-12-10",
    "tags": [
      "rap",
      "hip hop",
      "post-punk",
      "dubstep"
    ],
    "title": "Не буде",
    "totalTracks": 1,
    "type": "single",
    "url": "https://open.spotify.com/album/1rdXXjwJ0fHZ8IJNKQuE9r"
  },
  {
    "appearanceLog": [
      {
        "time": "2025-09-22T21:21:19.603Z",
        "type": "FOUND"
      }
    ],
    "artists": [
      "Alexjazz"
    ],
    "artistsPopularity": 3,
    "imageUrl": "https://i.scdn.co/image/ab67616d0000b273db0e16d2795d02d1db45cc2c",
    "releaseDate": "2021-06-25",
    "tags": [
      "post-punk"
    ],
    "title": "Гравітація",
    "totalTracks": 1,
    "type": "single",
    "url": "https://open.spotify.com/album/4YxiQYaz3LI7yDRrMOfe3m"
  },
  {
    "appearanceLog": [
      {
        "time": "2025-09-22T21:21:19.603Z",
        "type": "FOUND"
      }
    ],
    "artists": [
      "Alexjazz"
    ],
    "artistsPopularity": 3,
    "imageUrl": "https://i.scdn.co/image/ab67616d0000b273aa5d61b5049ec1765340fb91",
    "releaseDate": "2021-06-04",
    "tags": [
      "post-punk"
    ],
    "title": "Я люблю твої тихі затоки",
    "totalTracks": 1,
    "type": "single",
    "url": "https://open.spotify.com/album/6y5sP6Un1uEoyn4W2Op7CO"
  },
  {
    "appearanceLog": [
      {
        "time": "2025-09-22T21:21:19.603Z",
        "type": "FOUND"
      }
    ],
    "artists": [
      "Alexjazz"
    ],
    "artistsPopularity": 3,
    "imageUrl": "https://i.scdn.co/image/ab67616d0000b273050b66af2c2b67c3478d0040",
    "releaseDate": "2021-04-12",
    "tags": [
      "post-punk"
    ],
    "title": "Марс",
    "totalTracks": 1,
    "type": "single",
    "url": "https://open.spotify.com/album/5HL71OW0czaNDqqAAsOtgu"
  },
  {
    "appearanceLog": [
      {
        "time": "2025-09-22T21:21:19.603Z",
        "type": "FOUND"
      }
    ],
    "artists": [
      "Alexjazz"
    ],
    "artistsPopularity": 3,
    "imageUrl": "https://i.scdn.co/image/ab67616d0000b2739389a144ef761f0364cbccfd",
    "releaseDate": "2021-03-26",
    "tags": [
      "post-punk"
    ],
    "title": "Мій Ф'южн",
    "totalTracks": 1,
    "type": "single",
    "url": "https://open.spotify.com/album/6s5xLIYJHaQtfoJS4YK1CL"
  },
  {
    "appearanceLog": [
      {
        "time": "2025-09-22T21:21:19.603Z",
        "type": "FOUND"
      }
    ],
    "artists": [
      "Alexjazz"
    ],
    "artistsPopularity": 3,
    "imageUrl": "https://i.scdn.co/image/ab67616d0000b273b2bb0ea79964b38ca7eb453f",
    "releaseDate": "2018-08-15",
    "tags": [
      "post-punk"
    ],
    "title": "Hedonism",
    "totalTracks": 1,
    "type": "single",
    "url": "https://open.spotify.com/album/1CkvXIfV4wCMYk7c3uOBTZ"
  },
  {
    "appearanceLog": [
      {
        "time": "2025-09-22T21:21:19.603Z",
        "type": "FOUND"
      }
    ],
    "artists": [
      "Alexjazz"
    ],
    "artistsPopularity": 3,
    "imageUrl": "https://i.scdn.co/image/ab67616d0000b2730759b992c65a2287b3e9048c",
    "releaseDate": "2018-04-10",
    "tags": [
      "post-punk"
    ],
    "title": "Сьогодні",
    "totalTracks": 1,
    "type": "single",
    "url": "https://open.spotify.com/album/4XDRrzEgsfiN6y0xpJAaR0"
  },
  {
    "appearanceLog": [
      {
        "time": "2025-09-22T21:21:19.603Z",
        "type": "FOUND"
      }
    ],
    "artists": [
      "Artem Cheros",
      "Alexjazz"
    ],
    "artistsPopularity": 3,
    "imageUrl": "https://i.scdn.co/image/ab67616d0000b27303cbd944ea1f3a44390300f6",
    "releaseDate": "2016-04-10",
    "tags": [
      "post-punk"
    ],
    "title": "Мій будинок",
    "totalTracks": 1,
    "type": "single",
    "url": "https://open.spotify.com/album/1gdEXaa9sAwm2XeIVadHBL"
  },
  {
    "appearanceLog": [
      {
        "time": "2025-09-22T21:21:19.603Z",
        "type": "FOUND"
      }
    ],
    "artists": [
      "Alexjazz"
    ],
    "artistsPopularity": 3,
    "imageUrl": "https://i.scdn.co/image/ab67616d0000b273a3497c58731a5891a11002f3",
    "releaseDate": "2015-09-11",
    "tags": [
      "post-punk"
    ],
    "title": "Harvest",
    "totalTracks": 1,
    "type": "single",
    "url": "https://open.spotify.com/album/6utNtyZwjAcQxVSgB89ccF"
  },
  {
    "appearanceLog": [
      {
        "time": "2025-09-22T21:21:19.603Z",
        "type": "FOUND"
      }
    ],
    "artists": [
      "Alexjazz",
      "НастяЗникає",
      "Zombo"
    ],
    "artistsPopularity": 3,
    "imageUrl": "https://i.scdn.co/image/ab67616d0000b27398f26ae4d8e82296311945e3",
    "releaseDate": "2015-03-03",
    "tags": [
      "post-punk",
      "soul"
    ],
    "title": "Звуки",
    "totalTracks": 1,
    "type": "single",
    "url": "https://open.spotify.com/album/3aDCLsyafIog30zul0zGt3"
  },
  {
    "appearanceLog": [
      {
        "time": "2025-09-22T21:21:19.603Z",
        "type": "FOUND"
      }
    ],
    "artists": [
      "Alexjazz"
    ],
    "artistsPopularity": 3,
    "imageUrl": "https://i.scdn.co/image/ab67616d0000b27373ea98a13dd752dc24b26e31",
    "releaseDate": "2011-04-10",
    "tags": [
      "post-punk"
    ],
    "title": "Vibrations",
    "totalTracks": 6,
    "type": "single",
    "url": "https://open.spotify.com/album/6SPiFf7q5QCUn9wA7ZNYCi"
  },
  {
    "appearanceLog": [
      {
        "time": "2025-09-22T21:21:19.603Z",
        "type": "FOUND"
      }
    ],
    "artists": [
      "Загреб"
    ],
    "artistsPopularity": 3,
    "imageUrl": "https://i.scdn.co/image/ab67616d0000b273cf45e7734924425ec14d8301",
    "releaseDate": "2024-11-08",
    "tags": [
      "post-punk"
    ],
    "title": "Чотири",
    "totalTracks": 4,
    "type": "single",
    "url": "https://open.spotify.com/album/7t0QsZ0hzqpHeErtk9FyIl"
  },
  {
    "appearanceLog": [
      {
        "time": "2025-09-22T21:21:19.603Z",
        "type": "FOUND"
      }
    ],
    "artists": [
      "ВАТАГА"
    ],
    "artistsPopularity": 2,
    "imageUrl": "https://i.scdn.co/image/ab67616d0000b273a0bc333cc295baa8044cab8c",
    "releaseDate": "2022-03-31",
    "tags": [
      "hip hop",
      "rap",
      "underground hip-hop",
      "Hip-Hop"
    ],
    "title": "До зброї",
    "totalTracks": 1,
    "type": "single",
    "url": "https://open.spotify.com/album/2MPMpJc6YY1TyNGJ2DSSSk"
  },
  {
    "appearanceLog": [
      {
        "time": "2025-09-22T21:21:19.603Z",
        "type": "FOUND"
      }
    ],
    "artists": [
      "Sinuz"
    ],
    "artistsPopularity": 2,
    "imageUrl": "https://i.scdn.co/image/ab67616d0000b2734a7bf04403dfa4ae14daea2e",
    "releaseDate": "2017-12-31",
    "tags": [],
    "title": "Connexions",
    "totalTracks": 19,
    "type": "album",
    "url": "https://open.spotify.com/album/3PrSkrOajMIsN3U8qV503p"
  },
  {
    "appearanceLog": [
      {
        "time": "2025-09-22T21:21:19.603Z",
        "type": "FOUND"
      }
    ],
    "artists": [
      "Zombo"
    ],
    "artistsPopularity": 2,
    "imageUrl": "https://i.scdn.co/image/ab67616d0000b2735471ab483be8de9b76d2a993",
    "releaseDate": "2015-04-18",
    "tags": [],
    "title": "Атака букв",
    "totalTracks": 11,
    "type": "album",
    "url": "https://open.spotify.com/album/2pvJ2XnEkTM93I7B9oCjcz"
  },
  {
    "appearanceLog": [
      {
        "time": "2025-09-22T21:21:19.603Z",
        "type": "FOUND"
      }
    ],
    "artists": [
      "Artem Cheros"
    ],
    "artistsPopularity": 1,
    "imageUrl": "https://i.scdn.co/image/ab67616d0000b2737380b77d4cb7471777afc744",
    "releaseDate": "2018-03-01",
    "tags": [],
    "title": "Мій будинок",
    "totalTracks": 1,
    "type": "single",
    "url": "https://open.spotify.com/album/7zwWjr7jmGKt1Tqk9k03r8"
  },
  {
    "appearanceLog": [
      {
        "time": "2025-12-12T21:22:38.843Z",
        "type": "FOUND"
      }
    ],
    "artists": [
      "Alexjazz"
    ],
    "artistsPopularity": 3,
    "imageUrl": "https://i.scdn.co/image/ab67616d0000b273d1e775b11594ad25caeb5195",
    "releaseDate": "2025-12-12",
    "tags": [
      "post-punk"
    ],
    "title": "Алкоголь агоній",
    "totalTracks": 1,
    "type": "single",
    "url": "https://open.spotify.com/album/5euRt70yYfhMdaySSCit1Q"
  }
]