[
  {
    "appearanceLog": [
      {
        "time": "2025-10-16T14:21:48.123Z",
        "type": "FOUND"
      }
    ],
    "artists": [
      "Bulvar Lu"
    ],
    "artistsPopularity": 1,
    "imageUrl": "https://i.scdn.co/image/ab67616d0000b273970b6750a80412f2c26de405",
    "releaseDate": "2025-10-03",
    "tags": [],
    "title": "Під цим дощем",
    "totalTracks": 1,
    "type": "single",
    "url": "https://open.spotify.com/album/20DrElBqtofiXu3zLrTixr"
  },
  {
    "appearanceLog": [
      {
        "time": "2025-10-16T14:21:48.123Z",
        "type": "FOUND"
      }
    ],
    "artists": [
      "Bulvar Lu"
    ],
    "artistsPopularity": 1,
    "imageUrl": "https://i.scdn.co/image/ab67616d0000b2731b24d4869ae32daf5443c7be",
    "releaseDate": "2025-04-25",
    "tags": [],
    "title": "Парфум",
    "totalTracks": 1,
    "type": "single",
    "url": "https://open.spotify.com/album/2TkRmxjnfJyx2ly2d1yjkH"
  },
  {
    "appearanceLog": [
      {
        "time": "2025-10-16T14:21:48.123Z",
        "type": "FOUND"
      }
    ],
    "artists": [
      "Bulvar Lu"
    ],
    "artistsPopularity": 1,
    "imageUrl": "https://i.scdn.co/image/ab67616d0000b273299e4d564263cafb02e3ed32",
    "releaseDate": "2025-01-23",
    "tags": [],
    "title": "Обіцяй",
    "totalTracks": 1,
    "type": "single",
    "url": "https://open.spotify.com/album/3H1wlPz1FgyExkvx3DiXMH"
  },
  {
    "appearanceLog": [
      {
        "time": "2025-10-16T14:21:48.123Z",
        "type": "FOUND"
      }
    ],
    "artists": [
      "KOLA",
      "Bulvar Lu"
    ],
    "artistsPopularity": 4,
    "imageUrl": "https://i.scdn.co/image/ab67616d0000b273fd002e292e8e5390dfd2e171",
    "releaseDate": "2024-12-13",
    "tags": [
      "pop"
    ],
    "title": "Дотикам",
    "totalTracks": 1,
    "type": "single",
    "url": "https://open.spotify.com/album/60KnL5OJv9WbKgIyxQSo5y"
  },
  {
    "appearanceLog": [
      {
        "time": "2025-10-16T14:21:48.123Z",
        "type": "FOUND"
      }
    ],
    "artists": [
      "Bulvar Lu"
    ],
    "artistsPopularity": 1,
    "imageUrl": "https://i.scdn.co/image/ab67616d0000b27384c70435a5779ff94a8039f0",
    "releaseDate": "2024-10-24",
    "tags": [],
    "title": "Лелеки",
    "totalTracks": 1,
    "type": "single",
    "url": "https://open.spotify.com/album/22Pi871efqnFNCAXWOnle2"
  },
  {
    "appearanceLog": [
      {
        "time": "2025-10-16T14:21:48.123Z",
        "type": "FOUND"
      }
    ],
    "artists": [
      "TAYANNA",
      "Bulvar Lu"
    ],
    "artistsPopularity": 3,
    "imageUrl": "https://i.scdn.co/image/ab67616d0000b273b9aa060d2159386b1735d8c2",
    "releaseDate": "2024-08-30",
    "tags": [
      "pop",
      "Eurovision"
    ],
    "title": "Грішна кава",
    "totalTracks": 1,
    "type": "single",
    "url": "https://open.spotify.com/album/2PEMoVVAos1eyBFuTCkZXb"
  },
  {
    "appearanceLog": [
      {
        "time": "2025-10-16T14:21:48.123Z",
        "type": "FOUND"
      }
    ],
    "artists": [
      "Bulvar Lu"
    ],
    "artistsPopularity": 1,
    "imageUrl": "https://i.scdn.co/image/ab67616d0000b2737f0a768406acffa8f61f1d00",
    "releaseDate": "2024-07-11",
    "tags": [],
    "title": "Хуліганка",
    "totalTracks": 1,
    "type": "single",
    "url": "https://open.spotify.com/album/0RxjVWMBTLwtatx32K6RkY"
  },
  {
    "appearanceLog": [
      {
        "time": "2025-10-16T14:21:48.123Z",
        "type": "FOUND"
      }
    ],
    "artists": [
      "Bulvar Lu"
    ],
    "artistsPopularity": 1,
    "imageUrl": "https://i.scdn.co/image/ab67616d0000b273bb15b9fad30cb8e65e74dcf2",
    "releaseDate": "2024-05-03",
    "tags": [],
    "title": "Джеб в серце",
    "totalTracks": 1,
    "type": "single",
    "url": "https://open.spotify.com/album/3cPkWo7LmFFqn8uH7STTsK"
  },
  {
    "appearanceLog": [
      {
        "time": "2025-10-16T14:21:48.123Z",
        "type": "FOUND"
      }
    ],
    "artists": [
      "Bulvar Lu"
    ],
    "artistsPopularity": 1,
    "imageUrl": "https://i.scdn.co/image/ab67616d0000b2734b0c127fa597b5aecee03d6c",
    "releaseDate": "2024-03-06",
    "tags": [],
    "title": "По зіркам",
    "totalTracks": 1,
    "type": "single",
    "url": "https://open.spotify.com/album/0b34FptihjQ1FuASjvFNKN"
  },
  {
    "appearanceLog": [
      {
        "time": "2025-10-16T14:21:48.123Z",
        "type": "FOUND"
      }
    ],
    "artists": [
      "Bulvar Lu"
    ],
    "artistsPopularity": 1,
    "imageUrl": "https://i.scdn.co/image/ab67616d0000b273aeb9b517e75bf2b7f15f748f",
    "releaseDate": "2023-11-10",
    "tags": [],
    "title": "Незабутня",
    "totalTracks": 1,
    "type": "single",
    "url": "https://open.spotify.com/album/3CJ3umQNA5Cd89ZlHHYTvh"
  },
  {
    "appearanceLog": [
      {
        "time": "2025-10-16T14:21:48.123Z",
        "type": "FOUND"
      }
    ],
    "artists": [
      "Bulvar Lu"
    ],
    "artistsPopularity": 1,
    "imageUrl": "https://i.scdn.co/image/ab67616d0000b273fb2cdb82e41657d12a35ee5e",
    "releaseDate": "2022-08-05",
    "tags": [],
    "title": "Лютий",
    "totalTracks": 1,
    "type": "single",
    "url": "https://open.spotify.com/album/4dkHG7lISadlBfxcVZQxgF"
  },
  {
    "appearanceLog": [
      {
        "time": "2025-11-21T14:22:13.347Z",
        "type": "FOUND"
      }
    ],
    "artists": [
      "Bulvar Lu"
    ],
    "artistsPopularity": 1,
    "imageUrl": "https://i.scdn.co/image/ab67616d0000b273c3e37b20ee23918513d4015c",
    "releaseDate": "2025-11-21",
    "tags": [],
    "title": "Щасливі дні",
    "totalTracks": 1,
    "type": "single",
    "url": "https://open.spotify.com/album/3S1IqIzlRVnJfld6JhCJ5D"
  },
  {
    "appearanceLog": [
      {
        "time": "2025-12-16T14:23:05.171Z",
        "type": "FOUND"
      }
    ],
    "artists": [
      "Bulvar Lu",
      "Magnushevskyi"
    ],
    "artistsPopularity": 1,
    "imageUrl": "https://i.scdn.co/image/ab67616d0000b273b1223d9781aba84eff072242",
    "releaseDate": "2025-12-15",
    "tags": [],
    "title": "Щасливі дні (Magnushevskyi remix)",
    "totalTracks": 1,
    "type": "single",
    "url": "https://open.spotify.com/album/0qeFI1zpjJ2RtIOtOxEKsc"
  }
]