[
  {
    "appearanceLog": [
      {
        "time": "2025-10-11T16:22:05.546Z",
        "type": "FOUND"
      }
    ],
    "artists": [
      "Improvise Beats"
    ],
    "artistsPopularity": 1,
    "imageUrl": "https://i.scdn.co/image/ab67616d0000b273aa75896324b7d30060b19cd4",
    "releaseDate": "2024-08-05",
    "tags": [],
    "title": "Trapology",
    "totalTracks": 8,
    "type": "album",
    "url": "https://open.spotify.com/album/79xMrajmA1vL8rHpg9ddME"
  },
  {
    "appearanceLog": [
      {
        "time": "2025-10-11T16:22:05.546Z",
        "type": "FOUND"
      }
    ],
    "artists": [
      "Improvise Beats"
    ],
    "artistsPopularity": 1,
    "imageUrl": "https://i.scdn.co/image/ab67616d0000b27359da599e92f6aed1d97df9c0",
    "releaseDate": "2012-07-09",
    "tags": [],
    "title": "Цілком таємно",
    "totalTracks": 15,
    "type": "album",
    "url": "https://open.spotify.com/album/7u1szYbzxdT5eEfqmsxovZ"
  },
  {
    "appearanceLog": [
      {
        "time": "2025-10-11T16:22:05.546Z",
        "type": "FOUND"
      }
    ],
    "artists": [
      "Improvise Beats"
    ],
    "artistsPopularity": 1,
    "imageUrl": "https://i.scdn.co/image/ab67616d0000b27332408a7197ca00d4c88d2a29",
    "releaseDate": "2025-05-03",
    "tags": [],
    "title": "zabagato",
    "totalTracks": 1,
    "type": "single",
    "url": "https://open.spotify.com/album/1gzfshkAjJ3fTw2m3M569v"
  },
  {
    "appearanceLog": [
      {
        "time": "2025-10-11T16:22:05.546Z",
        "type": "FOUND"
      }
    ],
    "artists": [
      "Improvise Beats"
    ],
    "artistsPopularity": 1,
    "imageUrl": "https://i.scdn.co/image/ab67616d0000b273af1503b6ec1340d3d4b28aa3",
    "releaseDate": "2025-02-14",
    "tags": [],
    "title": "Nayobka Pt. 2",
    "totalTracks": 1,
    "type": "single",
    "url": "https://open.spotify.com/album/1CDsPZFQQSiHbioSAP2NQo"
  },
  {
    "appearanceLog": [
      {
        "time": "2025-10-11T16:22:05.546Z",
        "type": "FOUND"
      }
    ],
    "artists": [
      "Improvise Beats"
    ],
    "artistsPopularity": 1,
    "imageUrl": "https://i.scdn.co/image/ab67616d0000b273b3c5a199a0f853550f364607",
    "releaseDate": "2025-02-13",
    "tags": [],
    "title": "Intuition",
    "totalTracks": 1,
    "type": "single",
    "url": "https://open.spotify.com/album/1hUwgTRqZ4qWJ6YLXyr2Dk"
  },
  {
    "appearanceLog": [
      {
        "time": "2025-10-11T16:22:05.546Z",
        "type": "FOUND"
      }
    ],
    "artists": [
      "Improvise Beats"
    ],
    "artistsPopularity": 1,
    "imageUrl": "https://i.scdn.co/image/ab67616d0000b273f7d464fa6898b75431b69db5",
    "releaseDate": "2024-12-25",
    "tags": [],
    "title": "Mic Attack",
    "totalTracks": 1,
    "type": "single",
    "url": "https://open.spotify.com/album/6mBOVTxFIjuz2EiI6GWLsx"
  },
  {
    "appearanceLog": [
      {
        "time": "2025-10-11T16:22:05.546Z",
        "type": "FOUND"
      }
    ],
    "artists": [
      "Dimych",
      "Emson",
      "Improvise Beats"
    ],
    "artistsPopularity": 2,
    "imageUrl": "https://i.scdn.co/image/ab67616d0000b27380448f425b43544f817a665a",
    "releaseDate": "2024-12-14",
    "tags": [],
    "title": "Gitarka",
    "totalTracks": 1,
    "type": "single",
    "url": "https://open.spotify.com/album/3ppThSINxVIZ3peTOEKhZn"
  },
  {
    "appearanceLog": [
      {
        "time": "2025-10-11T16:22:05.546Z",
        "type": "FOUND"
      }
    ],
    "artists": [
      "Improvise Beats"
    ],
    "artistsPopularity": 1,
    "imageUrl": "https://i.scdn.co/image/ab67616d0000b273d8417a597d5af8979376b273",
    "releaseDate": "2024-09-20",
    "tags": [],
    "title": "Transience",
    "totalTracks": 1,
    "type": "single",
    "url": "https://open.spotify.com/album/6y2xmrVRlo6sgsWe0wqn7w"
  },
  {
    "appearanceLog": [
      {
        "time": "2025-10-11T16:22:05.546Z",
        "type": "FOUND"
      }
    ],
    "artists": [
      "Improvise Beats"
    ],
    "artistsPopularity": 1,
    "imageUrl": "https://i.scdn.co/image/ab67616d0000b273ac057d4abfeaf1fe3eb8e5ff",
    "releaseDate": "2024-08-24",
    "tags": [],
    "title": "очі кота",
    "totalTracks": 1,
    "type": "single",
    "url": "https://open.spotify.com/album/1LQprMUSBxKf4isTsyZV0K"
  },
  {
    "appearanceLog": [
      {
        "time": "2025-10-11T16:22:05.546Z",
        "type": "FOUND"
      }
    ],
    "artists": [
      "Improvise Beats"
    ],
    "artistsPopularity": 1,
    "imageUrl": "https://i.scdn.co/image/ab67616d0000b273091a36e08dbbf976254dc2a3",
    "releaseDate": "2024-07-09",
    "tags": [],
    "title": "Ra-ta-ta",
    "totalTracks": 1,
    "type": "single",
    "url": "https://open.spotify.com/album/74p91crRdZktoZT9l2OEK7"
  },
  {
    "appearanceLog": [
      {
        "time": "2025-10-11T16:22:05.546Z",
        "type": "FOUND"
      }
    ],
    "artists": [
      "Improvise Beats"
    ],
    "artistsPopularity": 1,
    "imageUrl": "https://i.scdn.co/image/ab67616d0000b27304663db5ebe1043071d70be8",
    "releaseDate": "2024-07-01",
    "tags": [],
    "title": "Перший сніг",
    "totalTracks": 1,
    "type": "single",
    "url": "https://open.spotify.com/album/39Yt1EtQe9sfQB9BYV1Rsv"
  },
  {
    "appearanceLog": [
      {
        "time": "2025-10-11T16:22:05.546Z",
        "type": "FOUND"
      }
    ],
    "artists": [
      "Improvise Beats"
    ],
    "artistsPopularity": 1,
    "imageUrl": "https://i.scdn.co/image/ab67616d0000b27386323fa81ba10cb0252989da",
    "releaseDate": "2024-06-29",
    "tags": [],
    "title": "Utopia World",
    "totalTracks": 1,
    "type": "single",
    "url": "https://open.spotify.com/album/1ZwD25b1BI5cX1FDnhggcG"
  },
  {
    "appearanceLog": [
      {
        "time": "2025-10-11T16:22:05.546Z",
        "type": "FOUND"
      }
    ],
    "artists": [
      "Improvise Beats"
    ],
    "artistsPopularity": 1,
    "imageUrl": "https://i.scdn.co/image/ab67616d0000b273dc620a929224443f38ea3fdb",
    "releaseDate": "2024-06-02",
    "tags": [],
    "title": "UA army",
    "totalTracks": 1,
    "type": "single",
    "url": "https://open.spotify.com/album/48kcy98IwFeSFxbObufIwC"
  },
  {
    "appearanceLog": [
      {
        "time": "2025-10-11T16:22:05.546Z",
        "type": "FOUND"
      }
    ],
    "artists": [
      "Improvise Beats"
    ],
    "artistsPopularity": 1,
    "imageUrl": "https://i.scdn.co/image/ab67616d0000b273dd629a35922fd0e9238dfb1c",
    "releaseDate": "2024-06-01",
    "tags": [],
    "title": "Капуста",
    "totalTracks": 1,
    "type": "single",
    "url": "https://open.spotify.com/album/11Mv0OajKLmIVJwXIF0jeb"
  },
  {
    "appearanceLog": [
      {
        "time": "2025-10-11T16:22:05.546Z",
        "type": "FOUND"
      }
    ],
    "artists": [
      "Improvise Beats"
    ],
    "artistsPopularity": 1,
    "imageUrl": "https://i.scdn.co/image/ab67616d0000b273a4915bb8c718f189382d5b28",
    "releaseDate": "2024-05-31",
    "tags": [],
    "title": "Нічого зайвого",
    "totalTracks": 1,
    "type": "single",
    "url": "https://open.spotify.com/album/6pph6y1rQ7C7Snve42LICp"
  },
  {
    "appearanceLog": [
      {
        "time": "2025-10-11T16:22:05.546Z",
        "type": "FOUND"
      }
    ],
    "artists": [
      "Improvise Beats"
    ],
    "artistsPopularity": 1,
    "imageUrl": "https://i.scdn.co/image/ab67616d0000b2739d292cade5be89307c71cb63",
    "releaseDate": "2024-05-30",
    "tags": [],
    "title": "Май на увазі",
    "totalTracks": 1,
    "type": "single",
    "url": "https://open.spotify.com/album/2xfSlPSkF00xQKkdDDUdti"
  },
  {
    "appearanceLog": [
      {
        "time": "2025-10-11T16:22:05.546Z",
        "type": "FOUND"
      }
    ],
    "artists": [
      "Improvise Beats"
    ],
    "artistsPopularity": 1,
    "imageUrl": "https://i.scdn.co/image/ab67616d0000b273e9eb53c3dfa10778f6fead0d",
    "releaseDate": "2024-01-05",
    "tags": [],
    "title": "Mlyn inn",
    "totalTracks": 1,
    "type": "single",
    "url": "https://open.spotify.com/album/0cByJnsgzRXSqt2EaKPQ0d"
  },
  {
    "appearanceLog": [
      {
        "time": "2025-10-11T16:22:05.546Z",
        "type": "FOUND"
      }
    ],
    "artists": [
      "Improvise Beats"
    ],
    "artistsPopularity": 1,
    "imageUrl": "https://i.scdn.co/image/ab67616d0000b27357990247724ce06537a9f26b",
    "releaseDate": "2023-08-05",
    "tags": [],
    "title": "Sad Space",
    "totalTracks": 1,
    "type": "single",
    "url": "https://open.spotify.com/album/7v29aKQHNLbCGHWBJRKRpD"
  },
  {
    "appearanceLog": [
      {
        "time": "2025-10-11T16:22:05.546Z",
        "type": "FOUND"
      }
    ],
    "artists": [
      "Improvise Beats"
    ],
    "artistsPopularity": 1,
    "imageUrl": "https://i.scdn.co/image/ab67616d0000b2732234eb165517ee4e8f361f9b",
    "releaseDate": "2023-06-19",
    "tags": [],
    "title": "DARKO",
    "totalTracks": 1,
    "type": "single",
    "url": "https://open.spotify.com/album/0K2NXZIjzAYvV0HghFjzBb"
  },
  {
    "appearanceLog": [
      {
        "time": "2025-10-11T16:22:05.546Z",
        "type": "FOUND"
      }
    ],
    "artists": [
      "Improvise Beats"
    ],
    "artistsPopularity": 1,
    "imageUrl": "https://i.scdn.co/image/ab67616d0000b27349ff4cd793301c9449d16623",
    "releaseDate": "2022-11-22",
    "tags": [],
    "title": "Dreams Come True 2020)",
    "totalTracks": 1,
    "type": "single",
    "url": "https://open.spotify.com/album/1tiS1EJyrum9LMsxvVjV5T"
  },
  {
    "appearanceLog": [
      {
        "time": "2025-10-11T16:22:05.546Z",
        "type": "FOUND"
      }
    ],
    "artists": [
      "Improvise Beats"
    ],
    "artistsPopularity": 1,
    "imageUrl": "https://i.scdn.co/image/ab67616d0000b273e25b39f67ee51d6ee96d3c61",
    "releaseDate": "2020-05-01",
    "tags": [],
    "title": "333666777",
    "totalTracks": 1,
    "type": "single",
    "url": "https://open.spotify.com/album/0HvHT0u7XfTi3dSedq07Gk"
  },
  {
    "appearanceLog": [
      {
        "time": "2025-10-11T16:22:05.546Z",
        "type": "FOUND"
      }
    ],
    "artists": [
      "Improvise Beats"
    ],
    "artistsPopularity": 1,
    "imageUrl": "https://i.scdn.co/image/ab67616d0000b273f8c69190a8ee2cb4834ac5d0",
    "releaseDate": "2019-01-07",
    "tags": [],
    "title": "репу шоб повно",
    "totalTracks": 1,
    "type": "single",
    "url": "https://open.spotify.com/album/4M9McLLUjzbHI9iSKsFmWv"
  },
  {
    "appearanceLog": [
      {
        "time": "2025-10-11T16:22:05.546Z",
        "type": "FOUND"
      }
    ],
    "artists": [
      "Improvise Beats"
    ],
    "artistsPopularity": 1,
    "imageUrl": "https://i.scdn.co/image/ab67616d0000b273be05bc42d3ce2ea51bc2732b",
    "releaseDate": "2014-06-13",
    "tags": [],
    "title": "Туман",
    "totalTracks": 1,
    "type": "single",
    "url": "https://open.spotify.com/album/17NvNfLUx9IEVZAvs8VOnO"
  },
  {
    "appearanceLog": [
      {
        "time": "2025-10-11T16:22:05.546Z",
        "type": "FOUND"
      }
    ],
    "artists": [
      "Improvise Beats"
    ],
    "artistsPopularity": 1,
    "imageUrl": "https://i.scdn.co/image/ab67616d0000b27339320154455501b283974a2b",
    "releaseDate": "2012-11-22",
    "tags": [],
    "title": "Чорнуха",
    "totalTracks": 6,
    "type": "single",
    "url": "https://open.spotify.com/album/75IJ4pOdjcwR1a5K8hCmkW"
  },
  {
    "appearanceLog": [
      {
        "time": "2025-10-11T16:22:05.546Z",
        "type": "FOUND"
      }
    ],
    "artists": [
      "Improvise Beats"
    ],
    "artistsPopularity": 1,
    "imageUrl": "https://i.scdn.co/image/ab67616d0000b27365d5534d95bf92c8c5edcc3c",
    "releaseDate": "2011-10-16",
    "tags": [],
    "title": "Faru",
    "totalTracks": 1,
    "type": "single",
    "url": "https://open.spotify.com/album/0CGZIrME3OzhriNYuGM8WH"
  },
  {
    "appearanceLog": [
      {
        "time": "2025-10-11T16:22:05.546Z",
        "type": "FOUND"
      }
    ],
    "artists": [
      "Improvise Beats"
    ],
    "artistsPopularity": 1,
    "imageUrl": "https://i.scdn.co/image/ab67616d0000b2738c6c53994b119b8f591f531f",
    "releaseDate": "2011-08-26",
    "tags": [],
    "title": "клинок правди 2011",
    "totalTracks": 1,
    "type": "single",
    "url": "https://open.spotify.com/album/7zrZvJlXon7SEzduWoJ7tV"
  },
  {
    "appearanceLog": [
      {
        "time": "2025-10-11T16:22:05.546Z",
        "type": "FOUND"
      }
    ],
    "artists": [
      "Improvise Beats"
    ],
    "artistsPopularity": 1,
    "imageUrl": "https://i.scdn.co/image/ab67616d0000b273f292ff3e94fb14a20933cc8d",
    "releaseDate": "2008-02-01",
    "tags": [],
    "title": "наша проблема",
    "totalTracks": 1,
    "type": "single",
    "url": "https://open.spotify.com/album/41q2uWosXRHYUdEP6UC5yl"
  },
  {
    "appearanceLog": [
      {
        "time": "2025-10-11T16:22:05.546Z",
        "type": "FOUND"
      }
    ],
    "artists": [
      "Nemo322"
    ],
    "artistsPopularity": 1,
    "imageUrl": "https://i.scdn.co/image/ab67616d0000b2734ca1970609d29bbf2ff71b41",
    "releaseDate": "2024-12-12",
    "tags": [
      "rap"
    ],
    "title": "Х.Л.А.М.2",
    "totalTracks": 20,
    "type": "album",
    "url": "https://open.spotify.com/album/3IRdXM3ekEZCHLUm1KTE7C"
  },
  {
    "appearanceLog": [
      {
        "time": "2025-10-11T16:22:05.546Z",
        "type": "FOUND"
      }
    ],
    "artists": [
      "Nemo322"
    ],
    "artistsPopularity": 1,
    "imageUrl": "https://i.scdn.co/image/ab67616d0000b273f738dfc317e253d87b2a51cb",
    "releaseDate": "2025-07-17",
    "tags": [
      "rap"
    ],
    "title": "RUBA",
    "totalTracks": 1,
    "type": "single",
    "url": "https://open.spotify.com/album/7meNnxxkE0hyGJ8olLwKMB"
  },
  {
    "appearanceLog": [
      {
        "time": "2025-10-11T16:22:05.546Z",
        "type": "FOUND"
      }
    ],
    "artists": [
      "Dimych"
    ],
    "artistsPopularity": 2,
    "imageUrl": "https://i.scdn.co/image/ab67616d0000b273dc84e2ccae946bee5673fefe",
    "releaseDate": "2025-06-08",
    "tags": [],
    "title": "В Такт",
    "totalTracks": 1,
    "type": "single",
    "url": "https://open.spotify.com/album/5rfcawpzbTo0Xp2RP32HIR"
  }
]