[
  {
    "appearanceLog": [
      {
        "time": "2025-09-17T07:24:53.612Z",
        "type": "FOUND"
      }
    ],
    "artists": [
      "The Soul Delusion"
    ],
    "artistsPopularity": 27,
    "imageUrl": "https://i.scdn.co/image/ab67616d0000b27302077b4332a11802db3ad950",
    "releaseDate": "2025-03-07",
    "tags": [
      "jazz",
      "soul"
    ],
    "title": "фарби забуття",
    "totalTracks": 4,
    "type": "single",
    "url": "https://open.spotify.com/album/2sy9aeifFkZIrmK2MyzpcX"
  },
  {
    "appearanceLog": [
      {
        "time": "2025-09-17T07:24:53.612Z",
        "type": "FOUND"
      }
    ],
    "artists": [
      "The Soul Delusion"
    ],
    "artistsPopularity": 27,
    "imageUrl": "https://i.scdn.co/image/ab67616d0000b27397cf0d83a4f895ee977fff36",
    "releaseDate": "2025-02-21",
    "tags": [
      "jazz",
      "soul"
    ],
    "title": "обережно! розбите!",
    "totalTracks": 1,
    "type": "single",
    "url": "https://open.spotify.com/album/7zH9MCmyBWI9P03w3mn34i"
  },
  {
    "appearanceLog": [
      {
        "time": "2025-09-17T07:24:53.612Z",
        "type": "FOUND"
      }
    ],
    "artists": [
      "The Soul Delusion"
    ],
    "artistsPopularity": 27,
    "imageUrl": "https://i.scdn.co/image/ab67616d0000b273f380ccc5569dac004e360828",
    "releaseDate": "2024-09-20",
    "tags": [
      "jazz",
      "soul"
    ],
    "title": "beyond",
    "totalTracks": 1,
    "type": "single",
    "url": "https://open.spotify.com/album/1CPWsfXazkDe39NZikd6M3"
  },
  {
    "appearanceLog": [
      {
        "time": "2025-09-17T07:24:53.612Z",
        "type": "FOUND"
      }
    ],
    "artists": [
      "The Soul Delusion"
    ],
    "artistsPopularity": 27,
    "imageUrl": "https://i.scdn.co/image/ab67616d0000b273a628332ca41463435e356023",
    "releaseDate": "2024-08-22",
    "tags": [
      "jazz",
      "soul"
    ],
    "title": "я є рана / я є ніж",
    "totalTracks": 1,
    "type": "single",
    "url": "https://open.spotify.com/album/1Xu46wHIEnQ86soI44DtmG"
  },
  {
    "appearanceLog": [
      {
        "time": "2025-09-17T07:24:53.612Z",
        "type": "FOUND"
      }
    ],
    "artists": [
      "The Soul Delusion"
    ],
    "artistsPopularity": 27,
    "imageUrl": "https://i.scdn.co/image/ab67616d0000b273df8dc9c89f17d8a616fd3813",
    "releaseDate": "2024-04-19",
    "tags": [
      "jazz",
      "soul"
    ],
    "title": "Навесні",
    "totalTracks": 1,
    "type": "single",
    "url": "https://open.spotify.com/album/7CWR6kNbMJ9hZpO0Dh1bcC"
  },
  {
    "appearanceLog": [
      {
        "time": "2025-09-17T07:24:53.612Z",
        "type": "FOUND"
      }
    ],
    "artists": [
      "The Soul Delusion"
    ],
    "artistsPopularity": 27,
    "imageUrl": "https://i.scdn.co/image/ab67616d0000b273ce668e6072ba65f57cd74c2a",
    "releaseDate": "2023-12-18",
    "tags": [
      "jazz",
      "soul"
    ],
    "title": "Blue Lizard Live Session",
    "totalTracks": 4,
    "type": "single",
    "url": "https://open.spotify.com/album/1l8YS3cbWnLZ8NISnGTh5F"
  },
  {
    "appearanceLog": [
      {
        "time": "2025-09-17T07:24:53.612Z",
        "type": "FOUND"
      }
    ],
    "artists": [
      "The Soul Delusion"
    ],
    "artistsPopularity": 27,
    "imageUrl": "https://i.scdn.co/image/ab67616d0000b273ba27b9ab4d426ed044a1b950",
    "releaseDate": "2023-08-31",
    "tags": [
      "jazz",
      "soul"
    ],
    "title": "Чую",
    "totalTracks": 1,
    "type": "single",
    "url": "https://open.spotify.com/album/3PlHYnR80YMkZX0JuP6efO"
  },
  {
    "appearanceLog": [
      {
        "time": "2025-09-17T07:24:53.612Z",
        "type": "FOUND"
      }
    ],
    "artists": [
      "The Soul Delusion"
    ],
    "artistsPopularity": 27,
    "imageUrl": "https://i.scdn.co/image/ab67616d0000b2736f2462919fcf1ac7bb01fceb",
    "releaseDate": "2023-08-02",
    "tags": [
      "jazz",
      "soul"
    ],
    "title": "Надіям",
    "totalTracks": 1,
    "type": "single",
    "url": "https://open.spotify.com/album/19MRIFrW0sYPGmPxPlGCmu"
  }
]