[
  {
    "appearanceLog": [
      {
        "time": "2025-09-23T03:24:27.843Z",
        "type": "FOUND"
      }
    ],
    "artists": [
      "Довгий Пес",
      "Wootabi"
    ],
    "artistsPopularity": 3,
    "imageUrl": "https://i.scdn.co/image/ab67616d0000b273122a7b65f8f80c744a26eea6",
    "releaseDate": "2024-02-09",
    "tags": [
      "rap"
    ],
    "title": "Холодриґґа",
    "totalTracks": 8,
    "type": "album",
    "url": "https://open.spotify.com/album/6MLckkaXXgWMosrwtbb5cO"
  },
  {
    "appearanceLog": [
      {
        "time": "2025-09-23T03:24:27.843Z",
        "type": "FOUND"
      }
    ],
    "artists": [
      "Довгий Пес"
    ],
    "artistsPopularity": 3,
    "imageUrl": "https://i.scdn.co/image/ab67616d0000b273f47d0831a56086f9777b4dfb",
    "releaseDate": "2020-02-25",
    "tags": [
      "rap"
    ],
    "title": "#олскул",
    "totalTracks": 12,
    "type": "album",
    "url": "https://open.spotify.com/album/5orXynjmfRph3dTaPLn3p4"
  },
  {
    "appearanceLog": [
      {
        "time": "2025-09-23T03:24:27.843Z",
        "type": "FOUND"
      }
    ],
    "artists": [
      "Довгий Пес"
    ],
    "artistsPopularity": 3,
    "imageUrl": "https://i.scdn.co/image/ab67616d0000b273928b82915134bf284338455c",
    "releaseDate": "2018-08-23",
    "tags": [
      "rap"
    ],
    "title": "#Соціальнийалкоголік",
    "totalTracks": 10,
    "type": "album",
    "url": "https://open.spotify.com/album/3ARGOPaQJ53UdA2dojjIiP"
  },
  {
    "appearanceLog": [
      {
        "time": "2025-09-23T03:24:27.843Z",
        "type": "FOUND"
      }
    ],
    "artists": [
      "Довгий Пес",
      "DJ Shon"
    ],
    "artistsPopularity": 3,
    "imageUrl": "https://i.scdn.co/image/ab67616d0000b27378ecc29dd722022ec0ebffcf",
    "releaseDate": "2017-10-17",
    "tags": [
      "rap",
      "instrumental hip-hop"
    ],
    "title": "Chill on Da Spot",
    "totalTracks": 8,
    "type": "album",
    "url": "https://open.spotify.com/album/3irEMXh7B2PERG0JEP4TnX"
  },
  {
    "appearanceLog": [
      {
        "time": "2025-09-23T03:24:27.843Z",
        "type": "FOUND"
      }
    ],
    "artists": [
      "Довгий Пес"
    ],
    "artistsPopularity": 3,
    "imageUrl": "https://i.scdn.co/image/ab67616d0000b273419cf59732bee40020a98e67",
    "releaseDate": "2025-09-11",
    "tags": [
      "rap"
    ],
    "title": "За горами гори",
    "totalTracks": 1,
    "type": "single",
    "url": "https://open.spotify.com/album/2Ye0AD3xlzqGh7A084voqr"
  },
  {
    "appearanceLog": [
      {
        "time": "2025-09-23T03:24:27.843Z",
        "type": "FOUND"
      }
    ],
    "artists": [
      "Довгий Пес",
      "Wootabi"
    ],
    "artistsPopularity": 3,
    "imageUrl": "https://i.scdn.co/image/ab67616d0000b273bdad9aae2290e3e3c6dea170",
    "releaseDate": "2025-02-14",
    "tags": [
      "rap"
    ],
    "title": "Спокій",
    "totalTracks": 2,
    "type": "single",
    "url": "https://open.spotify.com/album/0zexPhPgFjms5qxjIfp7uC"
  },
  {
    "appearanceLog": [
      {
        "time": "2025-09-23T03:24:27.843Z",
        "type": "FOUND"
      }
    ],
    "artists": [
      "Довгий Пес",
      "121",
      "Jointjay"
    ],
    "artistsPopularity": 3,
    "imageUrl": "https://i.scdn.co/image/ab67616d0000b2733c6e761f1e16cd76a5034aec",
    "releaseDate": "2025-01-29",
    "tags": [
      "rap",
      "abstract hip hop"
    ],
    "title": "Сенс є",
    "totalTracks": 1,
    "type": "single",
    "url": "https://open.spotify.com/album/2uYyZZsSmHY7tTUu2BqmTw"
  },
  {
    "appearanceLog": [
      {
        "time": "2025-09-23T03:24:27.843Z",
        "type": "FOUND"
      }
    ],
    "artists": [
      "Довгий Пес",
      "121"
    ],
    "artistsPopularity": 3,
    "imageUrl": "https://i.scdn.co/image/ab67616d0000b2731e73c842c2e1db3f8f433e43",
    "releaseDate": "2024-12-20",
    "tags": [
      "rap",
      "abstract hip hop"
    ],
    "title": "Дощ",
    "totalTracks": 1,
    "type": "single",
    "url": "https://open.spotify.com/album/7iulkmu82P0HaC16AjiXOv"
  },
  {
    "appearanceLog": [
      {
        "time": "2025-09-23T03:24:27.843Z",
        "type": "FOUND"
      }
    ],
    "artists": [
      "Довгий Пес",
      "121"
    ],
    "artistsPopularity": 3,
    "imageUrl": "https://i.scdn.co/image/ab67616d0000b2739e110b3c9c0cf473bd246bb0",
    "releaseDate": "2024-11-22",
    "tags": [
      "rap",
      "abstract hip hop"
    ],
    "title": "NPC",
    "totalTracks": 1,
    "type": "single",
    "url": "https://open.spotify.com/album/2Y7J2736XfGCZzf60sWcKz"
  },
  {
    "appearanceLog": [
      {
        "time": "2025-09-23T03:24:27.843Z",
        "type": "FOUND"
      }
    ],
    "artists": [
      "Довгий Пес",
      "121"
    ],
    "artistsPopularity": 3,
    "imageUrl": "https://i.scdn.co/image/ab67616d0000b27372e846500d6bc48a73a3dc83",
    "releaseDate": "2024-10-04",
    "tags": [
      "rap",
      "abstract hip hop"
    ],
    "title": "Спогади минулого життя",
    "totalTracks": 1,
    "type": "single",
    "url": "https://open.spotify.com/album/36FGFoI25Hbr3zCkSx00hK"
  },
  {
    "appearanceLog": [
      {
        "time": "2025-09-23T03:24:27.843Z",
        "type": "FOUND"
      }
    ],
    "artists": [
      "Довгий Пес",
      "121"
    ],
    "artistsPopularity": 3,
    "imageUrl": "https://i.scdn.co/image/ab67616d0000b273a728c8359def59efffb76697",
    "releaseDate": "2024-08-16",
    "tags": [
      "rap",
      "abstract hip hop"
    ],
    "title": "WOW",
    "totalTracks": 1,
    "type": "single",
    "url": "https://open.spotify.com/album/0r4njVIBmsiCpnfDCqoy8d"
  },
  {
    "appearanceLog": [
      {
        "time": "2025-09-23T03:24:27.843Z",
        "type": "FOUND"
      }
    ],
    "artists": [
      "Довгий Пес"
    ],
    "artistsPopularity": 3,
    "imageUrl": "https://i.scdn.co/image/ab67616d0000b273196381c7f5878ec80738ac5f",
    "releaseDate": "2024-07-26",
    "tags": [
      "rap"
    ],
    "title": "Метелик",
    "totalTracks": 1,
    "type": "single",
    "url": "https://open.spotify.com/album/4viPbrd8YkFTkO3fVWsi43"
  },
  {
    "appearanceLog": [
      {
        "time": "2025-09-23T03:24:27.843Z",
        "type": "FOUND"
      }
    ],
    "artists": [
      "Pero Culture Crew",
      "Довгий Пес",
      "Jointjay"
    ],
    "artistsPopularity": 3,
    "imageUrl": "https://i.scdn.co/image/ab67616d0000b273e743d47a5a8c6c56f3122bce",
    "releaseDate": "2024-05-01",
    "tags": [
      "rap"
    ],
    "title": "Avalanche (Jointjay Remix)",
    "totalTracks": 1,
    "type": "single",
    "url": "https://open.spotify.com/album/1L1yWUTefnv5JLYq9b0VOT"
  },
  {
    "appearanceLog": [
      {
        "time": "2025-09-23T03:24:27.843Z",
        "type": "FOUND"
      }
    ],
    "artists": [
      "Pero Culture Crew",
      "Довгий Пес",
      "DJ Shon"
    ],
    "artistsPopularity": 3,
    "imageUrl": "https://i.scdn.co/image/ab67616d0000b27386f4d5735a5dc32c6a565ad5",
    "releaseDate": "2024-03-27",
    "tags": [
      "rap",
      "instrumental hip-hop"
    ],
    "title": "Avalanche",
    "totalTracks": 1,
    "type": "single",
    "url": "https://open.spotify.com/album/2prhBbbe7ZUTd1Zl9Pv5gh"
  },
  {
    "appearanceLog": [
      {
        "time": "2025-09-23T03:24:27.843Z",
        "type": "FOUND"
      }
    ],
    "artists": [
      "Довгий Пес",
      "121"
    ],
    "artistsPopularity": 3,
    "imageUrl": "https://i.scdn.co/image/ab67616d0000b273f8c15815b11e2166e820c131",
    "releaseDate": "2024-01-29",
    "tags": [
      "rap",
      "abstract hip hop"
    ],
    "title": "Початок",
    "totalTracks": 1,
    "type": "single",
    "url": "https://open.spotify.com/album/6stWKVNqtv1eQTBvKljnXN"
  },
  {
    "appearanceLog": [
      {
        "time": "2025-09-23T03:24:27.843Z",
        "type": "FOUND"
      }
    ],
    "artists": [
      "Довгий Пес",
      "аппекс"
    ],
    "artistsPopularity": 3,
    "imageUrl": "https://i.scdn.co/image/ab67616d0000b2738e5c3b47878610b4539e6ff2",
    "releaseDate": "2023-12-08",
    "tags": [
      "rap",
      "abstract hip-hop"
    ],
    "title": "Куди дуля, туди й дим",
    "totalTracks": 1,
    "type": "single",
    "url": "https://open.spotify.com/album/2Tqvu4rPfhX67k09XfkOOv"
  },
  {
    "appearanceLog": [
      {
        "time": "2025-09-23T03:24:27.843Z",
        "type": "FOUND"
      }
    ],
    "artists": [
      "Довгий Пес",
      "ROPAN"
    ],
    "artistsPopularity": 3,
    "imageUrl": "https://i.scdn.co/image/ab67616d0000b2735092ca1b49bae45b83667b97",
    "releaseDate": "2023-10-13",
    "tags": [
      "rap",
      "reggae",
      "dub",
      "dancehall"
    ],
    "title": "Час випробовує мене",
    "totalTracks": 1,
    "type": "single",
    "url": "https://open.spotify.com/album/7cFz4AxFzkFyz8evp5xSBL"
  },
  {
    "appearanceLog": [
      {
        "time": "2025-09-23T03:24:27.843Z",
        "type": "FOUND"
      }
    ],
    "artists": [
      "Довгий Пес",
      "аппекс",
      "Haxxy"
    ],
    "artistsPopularity": 3,
    "imageUrl": "https://i.scdn.co/image/ab67616d0000b27325693056b9d79e60572cbfb9",
    "releaseDate": "2023-09-15",
    "tags": [
      "rap",
      "abstract hip-hop",
      "neurofunk",
      "Drum and bass"
    ],
    "title": "Течик на євробляхах",
    "totalTracks": 1,
    "type": "single",
    "url": "https://open.spotify.com/album/1fH1F2lOBbM4tCPAY04pr2"
  },
  {
    "appearanceLog": [
      {
        "time": "2025-09-23T03:24:27.843Z",
        "type": "FOUND"
      }
    ],
    "artists": [
      "RAPCHICK",
      "Довгий Пес"
    ],
    "artistsPopularity": 3,
    "imageUrl": "https://i.scdn.co/image/ab67616d0000b273280fe0912652079c7956652a",
    "releaseDate": "2023-08-25",
    "tags": [
      "rap"
    ],
    "title": "WEST SIDE",
    "totalTracks": 1,
    "type": "single",
    "url": "https://open.spotify.com/album/0rkaM4QVR3wC0mmeEkqMCV"
  },
  {
    "appearanceLog": [
      {
        "time": "2025-09-23T03:24:27.843Z",
        "type": "FOUND"
      }
    ],
    "artists": [
      "Довгий Пес",
      "Plugchoppa"
    ],
    "artistsPopularity": 3,
    "imageUrl": "https://i.scdn.co/image/ab67616d0000b27395e5f0c218ae5221e48a3c9b",
    "releaseDate": "2023-07-06",
    "tags": [
      "rap"
    ],
    "title": "НЙМ",
    "totalTracks": 1,
    "type": "single",
    "url": "https://open.spotify.com/album/3bAHmP79CmE6p73RKlLcTk"
  },
  {
    "appearanceLog": [
      {
        "time": "2025-09-23T03:24:27.843Z",
        "type": "FOUND"
      }
    ],
    "artists": [
      "Довгий Пес",
      "original dizzy"
    ],
    "artistsPopularity": 3,
    "imageUrl": "https://i.scdn.co/image/ab67616d0000b273a87cd4ac9178a6fce4627295",
    "releaseDate": "2023-06-16",
    "tags": [
      "rap"
    ],
    "title": "Танці під зірками",
    "totalTracks": 1,
    "type": "single",
    "url": "https://open.spotify.com/album/5mLhcQhFiLtadap3z4pLen"
  },
  {
    "appearanceLog": [
      {
        "time": "2025-09-23T03:24:27.843Z",
        "type": "FOUND"
      }
    ],
    "artists": [
      "Довгий Пес",
      "аппекс",
      "Jointjay"
    ],
    "artistsPopularity": 3,
    "imageUrl": "https://i.scdn.co/image/ab67616d0000b273366e42d2dfb057d4b5890f0b",
    "releaseDate": "2023-06-01",
    "tags": [
      "rap",
      "abstract hip-hop"
    ],
    "title": "Дивлюсь на район з вікна",
    "totalTracks": 1,
    "type": "single",
    "url": "https://open.spotify.com/album/7EkxPKRCJBnAk36kGUv0dx"
  },
  {
    "appearanceLog": [
      {
        "time": "2025-09-23T03:24:27.843Z",
        "type": "FOUND"
      }
    ],
    "artists": [
      "d1331",
      "Довгий Пес"
    ],
    "artistsPopularity": 3,
    "imageUrl": "https://i.scdn.co/image/ab67616d0000b2731acbe2123668a0befdf1b7ed",
    "releaseDate": "2023-05-19",
    "tags": [
      "rap"
    ],
    "title": "Куримо",
    "totalTracks": 1,
    "type": "single",
    "url": "https://open.spotify.com/album/4hG0cx5HQFei1R7kFegX2I"
  },
  {
    "appearanceLog": [
      {
        "time": "2025-09-23T03:24:27.843Z",
        "type": "FOUND"
      }
    ],
    "artists": [
      "Довгий Пес",
      "Jointjay"
    ],
    "artistsPopularity": 3,
    "imageUrl": "https://i.scdn.co/image/ab67616d0000b273e8641c2d9959ee7a4ceef0f8",
    "releaseDate": "2023-05-09",
    "tags": [
      "rap"
    ],
    "title": "Кавова культуррра",
    "totalTracks": 1,
    "type": "single",
    "url": "https://open.spotify.com/album/3JZwqdqdQsP9gN1AaSHGXP"
  },
  {
    "appearanceLog": [
      {
        "time": "2025-09-23T03:24:27.843Z",
        "type": "FOUND"
      }
    ],
    "artists": [
      "Довгий Пес",
      "MOEERR"
    ],
    "artistsPopularity": 3,
    "imageUrl": "https://i.scdn.co/image/ab67616d0000b27340d2e884bbabbad739dc4027",
    "releaseDate": "2023-05-02",
    "tags": [
      "rap"
    ],
    "title": "1000 казок",
    "totalTracks": 1,
    "type": "single",
    "url": "https://open.spotify.com/album/3Bp03g35woEGE7Cgt0hQyX"
  },
  {
    "appearanceLog": [
      {
        "time": "2025-09-23T03:24:27.843Z",
        "type": "FOUND"
      }
    ],
    "artists": [
      "Довгий Пес",
      "121"
    ],
    "artistsPopularity": 3,
    "imageUrl": "https://i.scdn.co/image/ab67616d0000b273ab7c2f22418b1c5e1399d50e",
    "releaseDate": "2023-04-20",
    "tags": [
      "rap",
      "abstract hip hop"
    ],
    "title": "ККК",
    "totalTracks": 1,
    "type": "single",
    "url": "https://open.spotify.com/album/1MyWSJzJE0XhMbHaGUoK3q"
  },
  {
    "appearanceLog": [
      {
        "time": "2025-09-23T03:24:27.843Z",
        "type": "FOUND"
      }
    ],
    "artists": [
      "Довгий Пес",
      "Wootabi"
    ],
    "artistsPopularity": 3,
    "imageUrl": "https://i.scdn.co/image/ab67616d0000b273ab4f423562abe3321331f6d3",
    "releaseDate": "2023-03-28",
    "tags": [
      "rap"
    ],
    "title": "Ціль",
    "totalTracks": 1,
    "type": "single",
    "url": "https://open.spotify.com/album/6vA4Ahf0xVak4nr4kkZVhQ"
  },
  {
    "appearanceLog": [
      {
        "time": "2025-09-23T03:24:27.843Z",
        "type": "FOUND"
      }
    ],
    "artists": [
      "Довгий Пес",
      "Jointjay"
    ],
    "artistsPopularity": 3,
    "imageUrl": "https://i.scdn.co/image/ab67616d0000b2735fb8cf090ea46704327002cd",
    "releaseDate": "2022-11-23",
    "tags": [
      "rap"
    ],
    "title": "Комендантська",
    "totalTracks": 1,
    "type": "single",
    "url": "https://open.spotify.com/album/37v3ELCo0n2ogCpjLryT7m"
  },
  {
    "appearanceLog": [
      {
        "time": "2025-09-23T03:24:27.843Z",
        "type": "FOUND"
      }
    ],
    "artists": [
      "Довгий Пес",
      "Jointjay"
    ],
    "artistsPopularity": 3,
    "imageUrl": "https://i.scdn.co/image/ab67616d0000b273855b91d640276e34bcdc2e5e",
    "releaseDate": "2022-09-07",
    "tags": [
      "rap"
    ],
    "title": "Стріляє реп",
    "totalTracks": 1,
    "type": "single",
    "url": "https://open.spotify.com/album/1JD9xGziCPi3mpGunx20kD"
  },
  {
    "appearanceLog": [
      {
        "time": "2025-09-23T03:24:27.843Z",
        "type": "FOUND"
      }
    ],
    "artists": [
      "Довгий Пес"
    ],
    "artistsPopularity": 3,
    "imageUrl": "https://i.scdn.co/image/ab67616d0000b27391b6b65e2c7113e21171ea83",
    "releaseDate": "2022-07-29",
    "tags": [
      "rap"
    ],
    "title": "Липа гарно пахне",
    "totalTracks": 1,
    "type": "single",
    "url": "https://open.spotify.com/album/4dI0aBduUV6rJKtINY4IlK"
  },
  {
    "appearanceLog": [
      {
        "time": "2025-09-23T03:24:27.843Z",
        "type": "FOUND"
      }
    ],
    "artists": [
      "Довгий Пес",
      "Jointjay"
    ],
    "artistsPopularity": 3,
    "imageUrl": "https://i.scdn.co/image/ab67616d0000b2738f6db4fe79b937224948839f",
    "releaseDate": "2022-07-12",
    "tags": [
      "rap"
    ],
    "title": "Ешкеричі",
    "totalTracks": 1,
    "type": "single",
    "url": "https://open.spotify.com/album/5S6R6xBAeKwfTrN12ps6h9"
  },
  {
    "appearanceLog": [
      {
        "time": "2025-09-23T03:24:27.843Z",
        "type": "FOUND"
      }
    ],
    "artists": [
      "Довгий Пес"
    ],
    "artistsPopularity": 3,
    "imageUrl": "https://i.scdn.co/image/ab67616d0000b273694ce20bfa8a4520c327dbb1",
    "releaseDate": "2022-05-11",
    "tags": [
      "rap"
    ],
    "title": "Колискова",
    "totalTracks": 1,
    "type": "single",
    "url": "https://open.spotify.com/album/1co49vfgxsOmKN8lS0zXPu"
  },
  {
    "appearanceLog": [
      {
        "time": "2025-09-23T03:24:27.843Z",
        "type": "FOUND"
      }
    ],
    "artists": [
      "Довгий Пес"
    ],
    "artistsPopularity": 3,
    "imageUrl": "https://i.scdn.co/image/ab67616d0000b27335d9bff0260788bbe21e074c",
    "releaseDate": "2022-03-30",
    "tags": [
      "rap"
    ],
    "title": "Невиспані",
    "totalTracks": 1,
    "type": "single",
    "url": "https://open.spotify.com/album/3OWlNmlnTUxQ71f9Pieiql"
  },
  {
    "appearanceLog": [
      {
        "time": "2025-09-23T03:24:27.843Z",
        "type": "FOUND"
      }
    ],
    "artists": [
      "Довгий Пес"
    ],
    "artistsPopularity": 3,
    "imageUrl": "https://i.scdn.co/image/ab67616d0000b273998a856195a4359c5667f6dc",
    "releaseDate": "2022-03-28",
    "tags": [
      "rap"
    ],
    "title": "Може б ти думав?",
    "totalTracks": 1,
    "type": "single",
    "url": "https://open.spotify.com/album/6TiehUIRvD4kqFwZUQlZqj"
  },
  {
    "appearanceLog": [
      {
        "time": "2025-09-23T03:24:27.843Z",
        "type": "FOUND"
      }
    ],
    "artists": [
      "Довгий Пес"
    ],
    "artistsPopularity": 3,
    "imageUrl": "https://i.scdn.co/image/ab67616d0000b2731af8a7089a88c4bffbe5f18f",
    "releaseDate": "2022-03-14",
    "tags": [
      "rap"
    ],
    "title": "ПІСНЯ НА ЄВРОБАЧЕННЯ",
    "totalTracks": 1,
    "type": "single",
    "url": "https://open.spotify.com/album/3CGOOEUYegR7sdWTNaSDqS"
  },
  {
    "appearanceLog": [
      {
        "time": "2025-09-23T03:24:27.843Z",
        "type": "FOUND"
      }
    ],
    "artists": [
      "Довгий Пес"
    ],
    "artistsPopularity": 3,
    "imageUrl": "https://i.scdn.co/image/ab67616d0000b273d4a2c2f5baafc03fb2cbaccc",
    "releaseDate": "2022-03-02",
    "tags": [
      "rap"
    ],
    "title": "У твій дім, для кентів і на район",
    "totalTracks": 1,
    "type": "single",
    "url": "https://open.spotify.com/album/0qYwXya9UYcWP4p9cv614X"
  },
  {
    "appearanceLog": [
      {
        "time": "2025-09-23T03:24:27.843Z",
        "type": "FOUND"
      }
    ],
    "artists": [
      "Довгий Пес"
    ],
    "artistsPopularity": 3,
    "imageUrl": "https://i.scdn.co/image/ab67616d0000b2731da8d119b82323967104c3a3",
    "releaseDate": "2021-12-03",
    "tags": [
      "rap"
    ],
    "title": "Чілений Кіт",
    "totalTracks": 1,
    "type": "single",
    "url": "https://open.spotify.com/album/1fimX9tgd1QfW01wi0xn3d"
  },
  {
    "appearanceLog": [
      {
        "time": "2025-09-23T03:24:27.843Z",
        "type": "FOUND"
      }
    ],
    "artists": [
      "Довгий Пес",
      "Jointjay"
    ],
    "artistsPopularity": 3,
    "imageUrl": "https://i.scdn.co/image/ab67616d0000b2734eb742576190175d60af68cd",
    "releaseDate": "2021-10-04",
    "tags": [
      "rap"
    ],
    "title": "Ставка на імені",
    "totalTracks": 1,
    "type": "single",
    "url": "https://open.spotify.com/album/36Ivqd6k7bHFfpie6EnL19"
  },
  {
    "appearanceLog": [
      {
        "time": "2025-09-23T03:24:27.843Z",
        "type": "FOUND"
      }
    ],
    "artists": [
      "Довгий Пес"
    ],
    "artistsPopularity": 3,
    "imageUrl": "https://i.scdn.co/image/ab67616d0000b273e58101d0fecec228e6d4a463",
    "releaseDate": "2021-06-29",
    "tags": [
      "rap"
    ],
    "title": "Від колиски до могили",
    "totalTracks": 1,
    "type": "single",
    "url": "https://open.spotify.com/album/71n7uCoJZRHkLTA80RnUCS"
  },
  {
    "appearanceLog": [
      {
        "time": "2025-09-23T03:24:27.843Z",
        "type": "FOUND"
      }
    ],
    "artists": [
      "Довгий Пес"
    ],
    "artistsPopularity": 3,
    "imageUrl": "https://i.scdn.co/image/ab67616d0000b273016f5d79ef8b569e2cd958bf",
    "releaseDate": "2021-04-20",
    "tags": [
      "rap"
    ],
    "title": "Пуф - пуф",
    "totalTracks": 1,
    "type": "single",
    "url": "https://open.spotify.com/album/5iMIyattGlEICwwi13o3yd"
  },
  {
    "appearanceLog": [
      {
        "time": "2025-09-23T03:24:27.843Z",
        "type": "FOUND"
      }
    ],
    "artists": [
      "Довгий Пес"
    ],
    "artistsPopularity": 3,
    "imageUrl": "https://i.scdn.co/image/ab67616d0000b273f743a77d114258babf40390f",
    "releaseDate": "2020-12-21",
    "tags": [
      "rap"
    ],
    "title": "Jointman",
    "totalTracks": 1,
    "type": "single",
    "url": "https://open.spotify.com/album/2ty12DQL5wjLRkwaXUNbhK"
  },
  {
    "appearanceLog": [
      {
        "time": "2025-09-23T03:24:27.843Z",
        "type": "FOUND"
      }
    ],
    "artists": [
      "Довгий Пес"
    ],
    "artistsPopularity": 3,
    "imageUrl": "https://i.scdn.co/image/ab67616d0000b2733d2d62c0ce3a411f845d7d63",
    "releaseDate": "2020-08-12",
    "tags": [
      "rap"
    ],
    "title": "Лайна П",
    "totalTracks": 1,
    "type": "single",
    "url": "https://open.spotify.com/album/4BQiBFiwP7AXfQ9eGWVFaB"
  },
  {
    "appearanceLog": [
      {
        "time": "2025-09-23T03:24:27.843Z",
        "type": "FOUND"
      }
    ],
    "artists": [
      "Довгий Пес"
    ],
    "artistsPopularity": 3,
    "imageUrl": "https://i.scdn.co/image/ab67616d0000b27375fe80b8b275a1165076681b",
    "releaseDate": "2020-05-27",
    "tags": [
      "rap"
    ],
    "title": "У лісі",
    "totalTracks": 1,
    "type": "single",
    "url": "https://open.spotify.com/album/4AuSR95FjNCFMh10sXtS9j"
  },
  {
    "appearanceLog": [
      {
        "time": "2025-09-23T03:24:27.843Z",
        "type": "FOUND"
      }
    ],
    "artists": [
      "Довгий Пес"
    ],
    "artistsPopularity": 3,
    "imageUrl": "https://i.scdn.co/image/ab67616d0000b2732b4157b8a94ca74b9c391b99",
    "releaseDate": "2020-02-25",
    "tags": [
      "rap"
    ],
    "title": "Мама принца хотіла",
    "totalTracks": 1,
    "type": "single",
    "url": "https://open.spotify.com/album/6T8UdyZxjYZoyYKpRF6Wxu"
  },
  {
    "appearanceLog": [
      {
        "time": "2025-09-23T03:24:27.843Z",
        "type": "FOUND"
      }
    ],
    "artists": [
      "Довгий Пес"
    ],
    "artistsPopularity": 3,
    "imageUrl": "https://i.scdn.co/image/ab67616d0000b2738eb8ba7e3b2399e949f46f26",
    "releaseDate": "2019-06-29",
    "tags": [
      "rap"
    ],
    "title": "У сірому кольорі",
    "totalTracks": 1,
    "type": "single",
    "url": "https://open.spotify.com/album/28E4eMgQvo1fhFpItYhNz2"
  },
  {
    "appearanceLog": [
      {
        "time": "2025-09-23T03:24:27.843Z",
        "type": "FOUND"
      }
    ],
    "artists": [
      "Довгий Пес"
    ],
    "artistsPopularity": 3,
    "imageUrl": "https://i.scdn.co/image/ab67616d0000b273c679e8b4d672b2a854646d23",
    "releaseDate": "2019-06-16",
    "tags": [
      "rap"
    ],
    "title": "Салют із провінції",
    "totalTracks": 1,
    "type": "single",
    "url": "https://open.spotify.com/album/4aYDqhyh0hTckhsVLuGiat"
  },
  {
    "appearanceLog": [
      {
        "time": "2025-09-23T03:24:27.843Z",
        "type": "FOUND"
      }
    ],
    "artists": [
      "Довгий Пес"
    ],
    "artistsPopularity": 3,
    "imageUrl": "https://i.scdn.co/image/ab67616d0000b2739a9b964da0d1dcbb66f13cf6",
    "releaseDate": "2019-01-30",
    "tags": [
      "rap"
    ],
    "title": "10 хвилин на березі моря",
    "totalTracks": 3,
    "type": "single",
    "url": "https://open.spotify.com/album/4vOHunVDXWAghCnQA5fImD"
  },
  {
    "appearanceLog": [
      {
        "time": "2025-09-23T03:24:27.843Z",
        "type": "FOUND"
      }
    ],
    "artists": [
      "Ядерна Могила"
    ],
    "artistsPopularity": 3,
    "imageUrl": "https://i.scdn.co/image/ab67616d0000b273f228e0109739efb7e6e90e90",
    "releaseDate": "2018-02-01",
    "tags": [
      "hip hop",
      "rap"
    ],
    "title": "Триптих",
    "totalTracks": 3,
    "type": "single",
    "url": "https://open.spotify.com/album/0xqjhU73tCDCiWNCDODgog"
  },
  {
    "appearanceLog": [
      {
        "time": "2025-09-23T03:24:27.843Z",
        "type": "FOUND"
      }
    ],
    "artists": [
      "аппекс"
    ],
    "artistsPopularity": 3,
    "imageUrl": "https://i.scdn.co/image/ab67616d0000b273aee354f2d9825762c72f977f",
    "releaseDate": "2021-04-27",
    "tags": [
      "abstract hip-hop"
    ],
    "title": "2",
    "totalTracks": 11,
    "type": "album",
    "url": "https://open.spotify.com/album/0BaDWr9fbkgr9u8UklSozH"
  },
  {
    "appearanceLog": [
      {
        "time": "2025-09-23T03:24:27.843Z",
        "type": "FOUND"
      }
    ],
    "artists": [
      "Тулим"
    ],
    "artistsPopularity": 3,
    "imageUrl": "https://i.scdn.co/image/ab67616d0000b273f07a2c45f5013d8dcd57468f",
    "releaseDate": "2016-03-15",
    "tags": [
      "hardcore rap",
      "underground rap"
    ],
    "title": "НЕТРІпанина",
    "totalTracks": 13,
    "type": "album",
    "url": "https://open.spotify.com/album/2mImGYOzS24fYBHvGmqxaY"
  },
  {
    "appearanceLog": [
      {
        "time": "2025-09-23T03:24:27.843Z",
        "type": "FOUND"
      }
    ],
    "artists": [
      "Гоня"
    ],
    "artistsPopularity": 3,
    "imageUrl": "https://i.scdn.co/image/ab67616d0000b273324f238d1002e697b38afa96",
    "releaseDate": "2020-06-19",
    "tags": [
      "rap"
    ],
    "title": "Бронепоїзд",
    "totalTracks": 1,
    "type": "single",
    "url": "https://open.spotify.com/album/7cOmxD305mEiPkhmyTaDTM"
  },
  {
    "appearanceLog": [
      {
        "time": "2025-09-23T03:24:27.843Z",
        "type": "FOUND"
      }
    ],
    "artists": [
      "Zombo",
      "Тулим"
    ],
    "artistsPopularity": 3,
    "imageUrl": "https://i.scdn.co/image/ab67616d0000b2738ef1b8bfeffaf84f849bf5bb",
    "releaseDate": "2021-09-16",
    "tags": [
      "hardcore rap",
      "underground rap"
    ],
    "title": "Маніфест",
    "totalTracks": 1,
    "type": "single",
    "url": "https://open.spotify.com/album/1k5f7U8sopR7fmr7jAdUly"
  },
  {
    "appearanceLog": [
      {
        "time": "2025-09-23T03:24:27.843Z",
        "type": "FOUND"
      }
    ],
    "artists": [
      "ВАТАГА"
    ],
    "artistsPopularity": 2,
    "imageUrl": "https://i.scdn.co/image/ab67616d0000b273a0bc333cc295baa8044cab8c",
    "releaseDate": "2022-03-31",
    "tags": [
      "hip hop",
      "rap",
      "underground hip-hop",
      "Hip-Hop"
    ],
    "title": "До зброї",
    "totalTracks": 1,
    "type": "single",
    "url": "https://open.spotify.com/album/2MPMpJc6YY1TyNGJ2DSSSk"
  },
  {
    "appearanceLog": [
      {
        "time": "2025-09-23T03:24:27.843Z",
        "type": "FOUND"
      }
    ],
    "artists": [
      "Various Artists"
    ],
    "artistsPopularity": 5,
    "imageUrl": "https://i.scdn.co/image/ab67616d0000b2732f013a630b5d5e048ce0704d",
    "releaseDate": "2025-09-05",
    "tags": [],
    "title": "#колоритму (Cypher)",
    "totalTracks": 1,
    "type": "single",
    "url": "https://open.spotify.com/album/5gvjJUEC2r2NvUs62pjQGk"
  },
  {
    "appearanceLog": [
      {
        "time": "2025-09-23T03:24:27.843Z",
        "type": "FOUND"
      }
    ],
    "artists": [
      "The Lazy Jesus"
    ],
    "artistsPopularity": 4,
    "imageUrl": "https://i.scdn.co/image/ab67616d0000b2731b7a21abed09dbbcc93901b1",
    "releaseDate": "2020-10-06",
    "tags": [
      "electronic"
    ],
    "title": "Original Fighter",
    "totalTracks": 8,
    "type": "album",
    "url": "https://open.spotify.com/album/4EOxbxXfaGo5LGkCR1Sfdo"
  },
  {
    "appearanceLog": [
      {
        "time": "2025-09-23T03:24:27.843Z",
        "type": "FOUND"
      }
    ],
    "artists": [
      "аппекс"
    ],
    "artistsPopularity": 3,
    "imageUrl": "https://i.scdn.co/image/ab67616d0000b273e9fc2c55346460744810dc7a",
    "releaseDate": "2019-11-29",
    "tags": [
      "abstract hip-hop"
    ],
    "title": "Служи собі",
    "totalTracks": 7,
    "type": "album",
    "url": "https://open.spotify.com/album/42XWZ1H4tiM87TV6B0QVFf"
  },
  {
    "appearanceLog": [
      {
        "time": "2025-09-23T03:24:27.843Z",
        "type": "FOUND"
      }
    ],
    "artists": [
      "ВАТАГА"
    ],
    "artistsPopularity": 2,
    "imageUrl": "https://i.scdn.co/image/ab67616d0000b27395998d9757788ffc5003c5ab",
    "releaseDate": "2023-06-13",
    "tags": [
      "hip hop",
      "rap",
      "underground hip-hop",
      "Hip-Hop"
    ],
    "title": "ПСАЙФЕР",
    "totalTracks": 1,
    "type": "single",
    "url": "https://open.spotify.com/album/4HmUHPMpRmuthtKU45A89l"
  },
  {
    "appearanceLog": [
      {
        "time": "2025-09-23T03:24:27.843Z",
        "type": "FOUND"
      }
    ],
    "artists": [
      "Nemo 322"
    ],
    "artistsPopularity": 1,
    "imageUrl": "https://i.scdn.co/image/ab67616d0000b273ee3884ee966ac41d464aad34",
    "releaseDate": "2018-12-19",
    "tags": [],
    "title": "X.л.а.м.",
    "totalTracks": 13,
    "type": "album",
    "url": "https://open.spotify.com/album/2AnMmg4WcCTcR3gX68pNRZ"
  },
  {
    "appearanceLog": [
      {
        "time": "2025-09-23T03:24:27.843Z",
        "type": "FOUND"
      }
    ],
    "artists": [
      "Тулим"
    ],
    "artistsPopularity": 3,
    "imageUrl": "https://i.scdn.co/image/ab67616d0000b2733290a4e0b4d9b17400a9a4db",
    "releaseDate": "2022-05-10",
    "tags": [
      "hardcore rap",
      "underground rap"
    ],
    "title": "Singlez n' featz, Vol.2",
    "totalTracks": 12,
    "type": "album",
    "url": "https://open.spotify.com/album/1hhVoytzN9l34yaH1iPeLH"
  },
  {
    "appearanceLog": [
      {
        "time": "2025-09-23T03:24:27.843Z",
        "type": "FOUND"
      }
    ],
    "artists": [
      "Jointjay"
    ],
    "artistsPopularity": 2,
    "imageUrl": "https://i.scdn.co/image/ab67616d0000b273f0c068e08da33b67bc832527",
    "releaseDate": "2025-09-12",
    "tags": [],
    "title": "Танці під зірками",
    "totalTracks": 1,
    "type": "single",
    "url": "https://open.spotify.com/album/5LacS2QSAXjSM2jYygrOk7"
  },
  {
    "appearanceLog": [
      {
        "time": "2025-09-23T03:24:27.843Z",
        "type": "FOUND"
      }
    ],
    "artists": [
      "Jointjay"
    ],
    "artistsPopularity": 2,
    "imageUrl": "https://i.scdn.co/image/ab67616d0000b273964267a73cf6c1288f4942c1",
    "releaseDate": "2023-07-07",
    "tags": [],
    "title": "Outbreak",
    "totalTracks": 5,
    "type": "single",
    "url": "https://open.spotify.com/album/5GcqS0pcHnAzkAzxjx834q"
  },
  {
    "appearanceLog": [
      {
        "time": "2025-09-23T03:24:27.843Z",
        "type": "FOUND"
      }
    ],
    "artists": [
      "Zombo",
      "Тулим"
    ],
    "artistsPopularity": 3,
    "imageUrl": "https://i.scdn.co/image/ab67616d0000b27301e520b6b559a1f1c8758d3b",
    "releaseDate": "2021-12-24",
    "tags": [
      "hardcore rap",
      "underground rap"
    ],
    "title": "Золоті часи",
    "totalTracks": 5,
    "type": "single",
    "url": "https://open.spotify.com/album/4do5oePF4xkRsKx9B1cZtP"
  },
  {
    "appearanceLog": [
      {
        "time": "2025-09-23T03:24:27.843Z",
        "type": "FOUND"
      }
    ],
    "artists": [
      "Zombo",
      "DJ Shon"
    ],
    "artistsPopularity": 2,
    "imageUrl": "https://i.scdn.co/image/ab67616d0000b273fef8dbc6b9311d9be0864131",
    "releaseDate": "2021-08-17",
    "tags": [
      "instrumental hip-hop"
    ],
    "title": "Comin` At Ya",
    "totalTracks": 12,
    "type": "album",
    "url": "https://open.spotify.com/album/7IppcWylLc4tXAaYeaLrGE"
  },
  {
    "appearanceLog": [
      {
        "time": "2025-09-23T03:24:27.843Z",
        "type": "FOUND"
      }
    ],
    "artists": [
      "Frazé-Frazénko"
    ],
    "artistsPopularity": 2,
    "imageUrl": "https://i.scdn.co/image/ab67616d0000b273b22a31d6387749c38236753d",
    "releaseDate": "2020-04-11",
    "tags": [],
    "title": "Наголос на Е",
    "totalTracks": 19,
    "type": "album",
    "url": "https://open.spotify.com/album/1dA7dwOXS1WvPf7rn5AjD5"
  },
  {
    "appearanceLog": [
      {
        "time": "2025-09-23T03:24:27.843Z",
        "type": "FOUND"
      }
    ],
    "artists": [
      "НЕформат"
    ],
    "artistsPopularity": 2,
    "imageUrl": "https://i.scdn.co/image/ab67616d0000b273ead3aaf3f366731990e6ce36",
    "releaseDate": "2021-07-07",
    "tags": [
      "rock",
      "rap",
      "hip hop"
    ],
    "title": "Голова",
    "totalTracks": 1,
    "type": "single",
    "url": "https://open.spotify.com/album/4QDUa541pzbuP91BuGKlH0"
  },
  {
    "appearanceLog": [
      {
        "time": "2025-09-23T03:24:27.843Z",
        "type": "FOUND"
      }
    ],
    "artists": [
      "Vendy Shmara"
    ],
    "artistsPopularity": 1,
    "imageUrl": "https://i.scdn.co/image/ab67616d0000b2735e54dface6c96b5d51d39324",
    "releaseDate": "2020-12-20",
    "tags": [],
    "title": "Голова",
    "totalTracks": 1,
    "type": "single",
    "url": "https://open.spotify.com/album/3aRCeAkG8mZ8AnzLUWwCzE"
  },
  {
    "appearanceLog": [
      {
        "time": "2025-09-23T03:24:27.843Z",
        "type": "FOUND"
      }
    ],
    "artists": [
      "Johnny Blaze"
    ],
    "artistsPopularity": 3,
    "imageUrl": "https://i.scdn.co/image/ab67616d0000b273278b42b015218db2699e47ec",
    "releaseDate": "2024-05-22",
    "tags": [
      "Hip-Hop"
    ],
    "title": "Холодрига",
    "totalTracks": 5,
    "type": "single",
    "url": "https://open.spotify.com/album/2PEMPZ4TKsYGrCuJCOBwX2"
  },
  {
    "appearanceLog": [
      {
        "time": "2025-09-23T03:24:27.843Z",
        "type": "FOUND"
      }
    ],
    "artists": [
      "Frazé-Frazénko"
    ],
    "artistsPopularity": 2,
    "imageUrl": "https://i.scdn.co/image/ab67616d0000b27349a1286d14a2545afce44610",
    "releaseDate": "2022-12-19",
    "tags": [],
    "title": "UA",
    "totalTracks": 13,
    "type": "album",
    "url": "https://open.spotify.com/album/0h3JaH6WJAiQRZi0L3KP9h"
  },
  {
    "appearanceLog": [
      {
        "time": "2025-09-23T03:24:27.843Z",
        "type": "FOUND"
      }
    ],
    "artists": [
      "Zombo"
    ],
    "artistsPopularity": 2,
    "imageUrl": "https://i.scdn.co/image/ab67616d0000b2736b7910ac2ff2b7a55435cac2",
    "releaseDate": "2022-11-16",
    "tags": [],
    "title": "Якось",
    "totalTracks": 1,
    "type": "single",
    "url": "https://open.spotify.com/album/19q2s0zkf6TL6vIIsbzKD1"
  },
  {
    "appearanceLog": [
      {
        "time": "2025-09-23T03:24:27.843Z",
        "type": "FOUND"
      }
    ],
    "artists": [
      "Крекер"
    ],
    "artistsPopularity": 2,
    "imageUrl": "https://i.scdn.co/image/ab67616d0000b273613fd6d481106e08b2602b19",
    "releaseDate": "2022-01-06",
    "tags": [],
    "title": "Реп кухня",
    "totalTracks": 1,
    "type": "single",
    "url": "https://open.spotify.com/album/1rmFS2zGQeht0hulx3Ot45"
  },
  {
    "appearanceLog": [
      {
        "time": "2025-09-23T03:24:27.843Z",
        "type": "FOUND"
      }
    ],
    "artists": [
      "DJ Shon",
      "Zombo"
    ],
    "artistsPopularity": 2,
    "imageUrl": "https://i.scdn.co/image/ab67616d0000b27388f2882173a67ad04c81e734",
    "releaseDate": "2020-02-20",
    "tags": [
      "instrumental hip-hop"
    ],
    "title": "Перезимуєм",
    "totalTracks": 1,
    "type": "single",
    "url": "https://open.spotify.com/album/3V2ODpqHtf8pr4SDjqDtU3"
  },
  {
    "appearanceLog": [
      {
        "time": "2025-10-04T03:22:25.867Z",
        "type": "FOUND"
      }
    ],
    "artists": [
      "ВАТАГА"
    ],
    "artistsPopularity": 2,
    "imageUrl": "https://i.scdn.co/image/ab67616d0000b273ad464a8b18f9f7ab5542101b",
    "releaseDate": "2025-10-03",
    "tags": [
      "rap",
      "Hip-Hop",
      "underground hip-hop"
    ],
    "title": "ЗБІР НА РЕБ (M-Squad)",
    "totalTracks": 1,
    "type": "single",
    "url": "https://open.spotify.com/album/5kVsYvhRXmDyhQ3dreoaPO"
  },
  {
    "appearanceLog": [
      {
        "time": "2025-10-09T03:26:34.406Z",
        "type": "FOUND"
      }
    ],
    "artists": [
      "Довгий Пес"
    ],
    "artistsPopularity": 3,
    "imageUrl": "https://i.scdn.co/image/ab67616d0000b273e1af3564805fb59d699199e0",
    "releaseDate": "2025-10-09",
    "tags": [
      "rap"
    ],
    "title": "Шишка із Закарпаття",
    "totalTracks": 1,
    "type": "single",
    "url": "https://open.spotify.com/album/4lkWiLViLC6H1ZVM0KUDjz"
  }
]